[{"CHANGE":"-","PLACE":1,"OLD":1,"NAME":"Roeders","ALTSCORE":"112364","DIFF":"72%","TOTAL_SCORE":"155888","FLAG":"se","REGION_NAME":"J\u00f6nk\u00f6ping","TOTAL_TAKES":"623","UNIQUE_ZONES":"363","DISTANCE":"270","DURATION":"21.3"},{"CHANGE":"-","PLACE":2,"OLD":2,"NAME":"brk","ALTSCORE":"99083","DIFF":"67%","TOTAL_SCORE":"147186","FLAG":"se","REGION_NAME":"J\u00f6nk\u00f6ping","TOTAL_TAKES":"665","UNIQUE_ZONES":"246","DISTANCE":"277","DURATION":"20.9"},{"CHANGE":"<nobr class=\"up\">+1<\/nobr>","PLACE":3,"OLD":4,"NAME":"Krocketkungen","ALTSCORE":"92671","DIFF":"84%","TOTAL_SCORE":"109229","FLAG":"se","REGION_NAME":"J\u00f6nk\u00f6ping","TOTAL_TAKES":"514","UNIQUE_ZONES":"238","DISTANCE":"319","DURATION":"34.5"},{"CHANGE":"<nobr class=\"up\">+1<\/nobr>","PLACE":4,"OLD":5,"NAME":"MissLi","ALTSCORE":"90773","DIFF":"83%","TOTAL_SCORE":"108976","FLAG":"se","REGION_NAME":"J\u00f6nk\u00f6ping","TOTAL_TAKES":"513","UNIQUE_ZONES":"236","DISTANCE":"299","DURATION":"34.6"},{"CHANGE":"<nobr class=\"up\">+1<\/nobr>","PLACE":5,"OLD":6,"NAME":"sockergurkan","ALTSCORE":"71532","DIFF":"73%","TOTAL_SCORE":"97126","FLAG":"se","REGION_NAME":"J\u00f6nk\u00f6ping","TOTAL_TAKES":"396","UNIQUE_ZONES":"210","DISTANCE":"179","DURATION":"19.4"},{"CHANGE":"<nobr class=\"down\">-3<\/nobr>","PLACE":6,"OLD":3,"NAME":"Nikki68","ALTSCORE":"58946","DIFF":"52%","TOTAL_SCORE":"111274","FLAG":"se","REGION_NAME":"J\u00f6nk\u00f6ping","TOTAL_TAKES":"475","UNIQUE_ZONES":"121","DISTANCE":"178","DURATION":"15.8"},{"CHANGE":"<nobr class=\"up\">+1<\/nobr>","PLACE":7,"OLD":8,"NAME":"Toubkal","ALTSCORE":"58354","DIFF":"66%","TOTAL_SCORE":"88405","FLAG":"se","REGION_NAME":"J\u00f6nk\u00f6ping","TOTAL_TAKES":"357","UNIQUE_ZONES":"164","DISTANCE":"128","DURATION":"13.2"},{"CHANGE":"<nobr class=\"up\">+3<\/nobr>","PLACE":8,"OLD":11,"NAME":"Dacop","ALTSCORE":"51961","DIFF":"82%","TOTAL_SCORE":"62716","FLAG":"se","REGION_NAME":"J\u00f6nk\u00f6ping","TOTAL_TAKES":"231","UNIQUE_ZONES":"178","DISTANCE":"106","DURATION":"8.1"},{"CHANGE":"<nobr class=\"up\">+4<\/nobr>","PLACE":9,"OLD":13,"NAME":"Game-Over","ALTSCORE":"49450","DIFF":"96%","TOTAL_SCORE":"51463","FLAG":"se","REGION_NAME":"J\u00f6nk\u00f6ping","TOTAL_TAKES":"229","UNIQUE_ZONES":"172","DISTANCE":" 87","DURATION":"7.1"},{"CHANGE":"<nobr class=\"down\">-3<\/nobr>","PLACE":10,"OLD":7,"NAME":"TakeAZone","ALTSCORE":"48186","DIFF":"50%","TOTAL_SCORE":"95103","FLAG":"se","REGION_NAME":"J\u00f6nk\u00f6ping","TOTAL_TAKES":"341","UNIQUE_ZONES":"87","DISTANCE":"178","DURATION":"20.2"},{"CHANGE":"<nobr class=\"down\">-1<\/nobr>","PLACE":11,"OLD":10,"NAME":"Lecl","ALTSCORE":"45357","DIFF":"70%","TOTAL_SCORE":"63940","FLAG":"se","REGION_NAME":"J\u00f6nk\u00f6ping","TOTAL_TAKES":"236","UNIQUE_ZONES":"151","DISTANCE":" 73","DURATION":"10.0"},{"CHANGE":"<nobr class=\"down\">-3<\/nobr>","PLACE":12,"OLD":9,"NAME":"Malaco","ALTSCORE":"44374","DIFF":"59%","TOTAL_SCORE":"74066","FLAG":"se","REGION_NAME":"J\u00f6nk\u00f6ping","TOTAL_TAKES":"335","UNIQUE_ZONES":"97","DISTANCE":"120","DURATION":"10.3"},{"CHANGE":"<nobr class=\"down\">-1<\/nobr>","PLACE":13,"OLD":12,"NAME":"geoturfwera","ALTSCORE":"41537","DIFF":"66%","TOTAL_SCORE":"62139","FLAG":"se","REGION_NAME":"J\u00f6nk\u00f6ping","TOTAL_TAKES":"186","UNIQUE_ZONES":"144","DISTANCE":" 75","DURATION":"7.9"},{"CHANGE":"-","PLACE":14,"OLD":14,"NAME":"runnerunn","ALTSCORE":"38097","DIFF":"76%","TOTAL_SCORE":"49960","FLAG":"se","REGION_NAME":"J\u00f6nk\u00f6ping","TOTAL_TAKES":"233","UNIQUE_ZONES":"86","DISTANCE":"125","DURATION":"10.5"},{"CHANGE":"<nobr class=\"up\">+8<\/nobr>","PLACE":15,"OLD":23,"NAME":"Badbalja","ALTSCORE":"35262","DIFF":"<nobr class=\"up\">102%<\/nobr>","TOTAL_SCORE":"34339","FLAG":"se","REGION_NAME":"J\u00f6nk\u00f6ping","TOTAL_TAKES":"175","UNIQUE_ZONES":"102","DISTANCE":" 94","DURATION":"13.0"},{"CHANGE":"<nobr class=\"up\">+1<\/nobr>","PLACE":16,"OLD":17,"NAME":"Provokat\u00f6r","ALTSCORE":"32401","DIFF":"80%","TOTAL_SCORE":"40174","FLAG":"se","REGION_NAME":"J\u00f6nk\u00f6ping","TOTAL_TAKES":"164","UNIQUE_ZONES":"100","DISTANCE":" 69","DURATION":"8.3"},{"CHANGE":"<nobr class=\"down\">-1<\/nobr>","PLACE":17,"OLD":16,"NAME":"Sabelhierta","ALTSCORE":"30492","DIFF":"75%","TOTAL_SCORE":"40577","FLAG":"se","REGION_NAME":"J\u00f6nk\u00f6ping","TOTAL_TAKES":"226","UNIQUE_ZONES":"69","DISTANCE":" 69","DURATION":"10.5"},{"CHANGE":"<nobr class=\"up\">+1<\/nobr>","PLACE":18,"OLD":19,"NAME":"hampewic","ALTSCORE":"29972","DIFF":"76%","TOTAL_SCORE":"39227","FLAG":"se","REGION_NAME":"J\u00f6nk\u00f6ping","TOTAL_TAKES":"166","UNIQUE_ZONES":"91","DISTANCE":" 56","DURATION":"5.8"},{"CHANGE":"<nobr class=\"up\">+2<\/nobr>","PLACE":19,"OLD":21,"NAME":"BWG","ALTSCORE":"27267","DIFF":"71%","TOTAL_SCORE":"38127","FLAG":"se","REGION_NAME":"J\u00f6nk\u00f6ping","TOTAL_TAKES":"151","UNIQUE_ZONES":"70","DISTANCE":" 81","DURATION":"13.3"},{"CHANGE":"<nobr class=\"down\">-5<\/nobr>","PLACE":20,"OLD":15,"NAME":"Charlie53","ALTSCORE":"26785","DIFF":"61%","TOTAL_SCORE":"43641","FLAG":"se","REGION_NAME":"J\u00f6nk\u00f6ping","TOTAL_TAKES":"208","UNIQUE_ZONES":"54","DISTANCE":" 77","DURATION":"12.1"},{"CHANGE":"<nobr class=\"down\">-1<\/nobr>","PLACE":21,"OLD":20,"NAME":"avante","ALTSCORE":"26570","DIFF":"69%","TOTAL_SCORE":"38444","FLAG":"se","REGION_NAME":"J\u00f6nk\u00f6ping","TOTAL_TAKES":"156","UNIQUE_ZONES":"73","DISTANCE":" 79","DURATION":"7.6"},{"CHANGE":"<nobr class=\"down\">-4<\/nobr>","PLACE":22,"OLD":18,"NAME":"krille68","ALTSCORE":"25147","DIFF":"62%","TOTAL_SCORE":"39966","FLAG":"se","REGION_NAME":"J\u00f6nk\u00f6ping","TOTAL_TAKES":"153","UNIQUE_ZONES":"70","DISTANCE":" 55","DURATION":"7.2"},{"CHANGE":"<nobr class=\"down\">-1<\/nobr>","PLACE":23,"OLD":22,"NAME":"01Kenna","ALTSCORE":"24925","DIFF":"68%","TOTAL_SCORE":"36537","FLAG":"se","REGION_NAME":"J\u00f6nk\u00f6ping","TOTAL_TAKES":"153","UNIQUE_ZONES":"66","DISTANCE":" 60","DURATION":"4.7"},{"CHANGE":"<nobr class=\"up\">+1<\/nobr>","PLACE":24,"OLD":25,"NAME":"Gravedigger","ALTSCORE":"23294","DIFF":"75%","TOTAL_SCORE":"30900","FLAG":"se","REGION_NAME":"J\u00f6nk\u00f6ping","TOTAL_TAKES":"132","UNIQUE_ZONES":"70","DISTANCE":" 43","DURATION":"6.4"},{"CHANGE":"<nobr class=\"up\">+3<\/nobr>","PLACE":25,"OLD":28,"NAME":"iras","ALTSCORE":"21424","DIFF":"89%","TOTAL_SCORE":"23875","FLAG":"se","REGION_NAME":"J\u00f6nk\u00f6ping","TOTAL_TAKES":"114","UNIQUE_ZONES":"63","DISTANCE":" 47","DURATION":"7.0"},{"CHANGE":"<nobr class=\"down\">-2<\/nobr>","PLACE":26,"OLD":24,"NAME":"S53","ALTSCORE":"20395","DIFF":"65%","TOTAL_SCORE":"31317","FLAG":"se","REGION_NAME":"J\u00f6nk\u00f6ping","TOTAL_TAKES":"86","UNIQUE_ZONES":"67","DISTANCE":" 59","DURATION":"6.3"},{"CHANGE":"<nobr class=\"up\">+9<\/nobr>","PLACE":27,"OLD":36,"NAME":"Tompa52","ALTSCORE":"19852","DIFF":"<nobr class=\"up\">104%<\/nobr>","TOTAL_SCORE":"18982","FLAG":"se","REGION_NAME":"J\u00f6nk\u00f6ping","TOTAL_TAKES":"82","UNIQUE_ZONES":"66","DISTANCE":" 43","DURATION":"6.0"},{"CHANGE":"<nobr class=\"up\">+4<\/nobr>","PLACE":28,"OLD":32,"NAME":"Darcy","ALTSCORE":"19488","DIFF":"96%","TOTAL_SCORE":"20206","FLAG":"se","REGION_NAME":"J\u00f6nk\u00f6ping","TOTAL_TAKES":"74","UNIQUE_ZONES":"59","DISTANCE":" 60","DURATION":"5.4"},{"CHANGE":"<nobr class=\"up\">+5<\/nobr>","PLACE":29,"OLD":34,"NAME":"MadMajk","ALTSCORE":"18294","DIFF":"93%","TOTAL_SCORE":"19491","FLAG":"se","REGION_NAME":"J\u00f6nk\u00f6ping","TOTAL_TAKES":"91","UNIQUE_ZONES":"61","DISTANCE":" 27","DURATION":"2.9"},{"CHANGE":"<nobr class=\"down\">-4<\/nobr>","PLACE":30,"OLD":26,"NAME":"JenHill","ALTSCORE":"17908","DIFF":"65%","TOTAL_SCORE":"27370","FLAG":"se","REGION_NAME":"J\u00f6nk\u00f6ping","TOTAL_TAKES":"103","UNIQUE_ZONES":"51","DISTANCE":" 37","DURATION":"7.5"},{"CHANGE":"<nobr class=\"up\">+7<\/nobr>","PLACE":31,"OLD":38,"NAME":"SwedishSinatra","ALTSCORE":"17830","DIFF":"<nobr class=\"up\">103%<\/nobr>","TOTAL_SCORE":"17287","FLAG":"se","REGION_NAME":"J\u00f6nk\u00f6ping","TOTAL_TAKES":"62","UNIQUE_ZONES":"55","DISTANCE":" 57","DURATION":"5.1"},{"CHANGE":"<nobr class=\"up\">+7<\/nobr>","PLACE":32,"OLD":39,"NAME":"vanderbelgien","ALTSCORE":"16513","DIFF":"96%","TOTAL_SCORE":"17144","FLAG":"se","REGION_NAME":"J\u00f6nk\u00f6ping","TOTAL_TAKES":"66","UNIQUE_ZONES":"52","DISTANCE":" 44","DURATION":"3.2"},{"CHANGE":"<nobr class=\"down\">-2<\/nobr>","PLACE":33,"OLD":31,"NAME":"NydalaElin","ALTSCORE":"16273","DIFF":"70%","TOTAL_SCORE":"23195","FLAG":"se","REGION_NAME":"J\u00f6nk\u00f6ping","TOTAL_TAKES":"122","UNIQUE_ZONES":"38","DISTANCE":" 32","DURATION":"8.2"},{"CHANGE":"<nobr class=\"down\">-4<\/nobr>","PLACE":34,"OLD":30,"NAME":"ronol59","ALTSCORE":"15675","DIFF":"66%","TOTAL_SCORE":"23560","FLAG":"se","REGION_NAME":"J\u00f6nk\u00f6ping","TOTAL_TAKES":"79","UNIQUE_ZONES":"53","DISTANCE":" 31","DURATION":"3.5"},{"CHANGE":"<nobr class=\"down\">-8<\/nobr>","PLACE":35,"OLD":27,"NAME":"abco","ALTSCORE":"15228","DIFF":"63%","TOTAL_SCORE":"23887","FLAG":"se","REGION_NAME":"J\u00f6nk\u00f6ping","TOTAL_TAKES":"68","UNIQUE_ZONES":"54","DISTANCE":" 23","DURATION":"3.7"},{"CHANGE":"<nobr class=\"down\">-7<\/nobr>","PLACE":36,"OLD":29,"NAME":"Liza46","ALTSCORE":"15103","DIFF":"63%","TOTAL_SCORE":"23610","FLAG":"se","REGION_NAME":"J\u00f6nk\u00f6ping","TOTAL_TAKES":"106","UNIQUE_ZONES":"36","DISTANCE":" 38","DURATION":"11.1"},{"CHANGE":"<nobr class=\"up\">+11<\/nobr>","PLACE":37,"OLD":48,"NAME":"asian1004","ALTSCORE":"14845","DIFF":"<nobr class=\"up\">110%<\/nobr>","TOTAL_SCORE":"13391","FLAG":"se","REGION_NAME":"J\u00f6nk\u00f6ping","TOTAL_TAKES":"85","UNIQUE_ZONES":"47","DISTANCE":" 19","DURATION":"9.0"},{"CHANGE":"<nobr class=\"down\">-3<\/nobr>","PLACE":38,"OLD":35,"NAME":"Lae","ALTSCORE":"14160","DIFF":"74%","TOTAL_SCORE":"19125","FLAG":"se","REGION_NAME":"J\u00f6nk\u00f6ping","TOTAL_TAKES":"56","UNIQUE_ZONES":"53","DISTANCE":" 18","DURATION":"3.0"},{"CHANGE":"<nobr class=\"up\">+3<\/nobr>","PLACE":39,"OLD":42,"NAME":"Bj\u00f6rneberg","ALTSCORE":"13026","DIFF":"83%","TOTAL_SCORE":"15687","FLAG":"se","REGION_NAME":"J\u00f6nk\u00f6ping","TOTAL_TAKES":"53","UNIQUE_ZONES":"49","DISTANCE":" 18","DURATION":"4.6"},{"CHANGE":"<nobr class=\"up\">+7<\/nobr>","PLACE":40,"OLD":47,"NAME":"sunekantarel","ALTSCORE":"12672","DIFF":"94%","TOTAL_SCORE":"13396","FLAG":"se","REGION_NAME":"J\u00f6nk\u00f6ping","TOTAL_TAKES":"64","UNIQUE_ZONES":"50","DISTANCE":"  0","DURATION":"0.0"},{"CHANGE":"<nobr class=\"down\">-8<\/nobr>","PLACE":41,"OLD":33,"NAME":"Hawk65","ALTSCORE":"12454","DIFF":"62%","TOTAL_SCORE":"19950","FLAG":"se","REGION_NAME":"J\u00f6nk\u00f6ping","TOTAL_TAKES":"61","UNIQUE_ZONES":"39","DISTANCE":" 25","DURATION":"3.6"},{"CHANGE":"<nobr class=\"down\">-2<\/nobr>","PLACE":42,"OLD":40,"NAME":"Oaklake","ALTSCORE":"11689","DIFF":"69%","TOTAL_SCORE":"16823","FLAG":"se","REGION_NAME":"J\u00f6nk\u00f6ping","TOTAL_TAKES":"54","UNIQUE_ZONES":"41","DISTANCE":" 15","DURATION":"2.0"},{"CHANGE":"<nobr class=\"up\">+6<\/nobr>","PLACE":43,"OLD":49,"NAME":"odal","ALTSCORE":"11262","DIFF":"86%","TOTAL_SCORE":"13001","FLAG":"se","REGION_NAME":"J\u00f6nk\u00f6ping","TOTAL_TAKES":"47","UNIQUE_ZONES":"46","DISTANCE":"  4","DURATION":"1.0"},{"CHANGE":"<nobr class=\"up\">+1<\/nobr>","PLACE":44,"OLD":45,"NAME":"MawrikJKPG","ALTSCORE":"10956","DIFF":"74%","TOTAL_SCORE":"14730","FLAG":"se","REGION_NAME":"J\u00f6nk\u00f6ping","TOTAL_TAKES":"62","UNIQUE_ZONES":"41","DISTANCE":"  0","DURATION":"0.0"},{"CHANGE":"<nobr class=\"down\">-2<\/nobr>","PLACE":45,"OLD":43,"NAME":"Nytj\u00e4rn","ALTSCORE":"10949","DIFF":"72%","TOTAL_SCORE":"15136","FLAG":"se","REGION_NAME":"J\u00f6nk\u00f6ping","TOTAL_TAKES":"65","UNIQUE_ZONES":"40","DISTANCE":"  0","DURATION":"0.0"},{"CHANGE":"<nobr class=\"up\">+8<\/nobr>","PLACE":46,"OLD":54,"NAME":"RoadRacer","ALTSCORE":"10842","DIFF":"95%","TOTAL_SCORE":"11307","FLAG":"se","REGION_NAME":"J\u00f6nk\u00f6ping","TOTAL_TAKES":"60","UNIQUE_ZONES":"41","DISTANCE":"  0","DURATION":"0.0"},{"CHANGE":"<nobr class=\"down\">-1<\/nobr>","PLACE":47,"OLD":46,"NAME":"Guddan","ALTSCORE":"10599","DIFF":"76%","TOTAL_SCORE":"13892","FLAG":"se","REGION_NAME":"J\u00f6nk\u00f6ping","TOTAL_TAKES":"62","UNIQUE_ZONES":"39","DISTANCE":"  0","DURATION":"0.0"},{"CHANGE":"<nobr class=\"up\">+2<\/nobr>","PLACE":48,"OLD":50,"NAME":"monica64","ALTSCORE":"10226","DIFF":"79%","TOTAL_SCORE":"12881","FLAG":"se","REGION_NAME":"J\u00f6nk\u00f6ping","TOTAL_TAKES":"50","UNIQUE_ZONES":"39","DISTANCE":"  4","DURATION":"0.5"},{"CHANGE":"<nobr class=\"down\">-8<\/nobr>","PLACE":49,"OLD":41,"NAME":"iRonNuke","ALTSCORE":"10170","DIFF":"61%","TOTAL_SCORE":"16559","FLAG":"se","REGION_NAME":"J\u00f6nk\u00f6ping","TOTAL_TAKES":"72","UNIQUE_ZONES":"23","DISTANCE":" 25","DURATION":"6.3"},{"CHANGE":"<nobr class=\"up\">+2<\/nobr>","PLACE":50,"OLD":52,"NAME":"19JakeBauer","ALTSCORE":"9980","DIFF":"78%","TOTAL_SCORE":"12712","FLAG":"se","REGION_NAME":"J\u00f6nk\u00f6ping","TOTAL_TAKES":"44","UNIQUE_ZONES":"36","DISTANCE":" 13","DURATION":"1.2"},{"CHANGE":"<nobr class=\"down\">-7<\/nobr>","PLACE":51,"OLD":44,"NAME":"mallan92","ALTSCORE":"9884","DIFF":"65%","TOTAL_SCORE":"15049","FLAG":"se","REGION_NAME":"J\u00f6nk\u00f6ping","TOTAL_TAKES":"50","UNIQUE_ZONES":"31","DISTANCE":" 18","DURATION":"2.0"},{"CHANGE":"<nobr class=\"up\">+1<\/nobr>","PLACE":52,"OLD":53,"NAME":"1selma","ALTSCORE":"9629","DIFF":"80%","TOTAL_SCORE":"11906","FLAG":"se","REGION_NAME":"J\u00f6nk\u00f6ping","TOTAL_TAKES":"48","UNIQUE_ZONES":"31","DISTANCE":" 16","DURATION":"3.4"},{"CHANGE":"<nobr class=\"down\">-2<\/nobr>","PLACE":53,"OLD":51,"NAME":"ozi","ALTSCORE":"8678","DIFF":"68%","TOTAL_SCORE":"12732","FLAG":"se","REGION_NAME":"J\u00f6nk\u00f6ping","TOTAL_TAKES":"53","UNIQUE_ZONES":"24","DISTANCE":" 17","DURATION":"2.8"},{"CHANGE":"<nobr class=\"down\">-17<\/nobr>","PLACE":54,"OLD":37,"NAME":"giggiyd","ALTSCORE":"8511","DIFF":"48%","TOTAL_SCORE":"17434","FLAG":"se","REGION_NAME":"J\u00f6nk\u00f6ping","TOTAL_TAKES":"68","UNIQUE_ZONES":"19","DISTANCE":" 15","DURATION":"4.1"},{"CHANGE":"<nobr class=\"up\">+6<\/nobr>","PLACE":55,"OLD":61,"NAME":"broccoliA-M","ALTSCORE":"8325","DIFF":"<nobr class=\"up\">108%<\/nobr>","TOTAL_SCORE":"7651","FLAG":"se","REGION_NAME":"J\u00f6nk\u00f6ping","TOTAL_TAKES":"37","UNIQUE_ZONES":"30","DISTANCE":" 10","DURATION":"1.5"},{"CHANGE":"<nobr class=\"down\">-1<\/nobr>","PLACE":56,"OLD":55,"NAME":"tpcc60","ALTSCORE":"8274","DIFF":"74%","TOTAL_SCORE":"11073","FLAG":"se","REGION_NAME":"J\u00f6nk\u00f6ping","TOTAL_TAKES":"39","UNIQUE_ZONES":"28","DISTANCE":" 13","DURATION":"4.7"},{"CHANGE":"<nobr class=\"up\">+1<\/nobr>","PLACE":57,"OLD":58,"NAME":"w.nytjarn","ALTSCORE":"8254","DIFF":"98%","TOTAL_SCORE":"8420","FLAG":"se","REGION_NAME":"J\u00f6nk\u00f6ping","TOTAL_TAKES":"43","UNIQUE_ZONES":"32","DISTANCE":"  0","DURATION":"0.0"},{"CHANGE":"<nobr class=\"up\">+6<\/nobr>","PLACE":58,"OLD":64,"NAME":"Bl\u00e5klinten","ALTSCORE":"7065","DIFF":"<nobr class=\"up\">102%<\/nobr>","TOTAL_SCORE":"6891","FLAG":"se","REGION_NAME":"J\u00f6nk\u00f6ping","TOTAL_TAKES":"38","UNIQUE_ZONES":"27","DISTANCE":"  0","DURATION":"0.0"},{"CHANGE":"<nobr class=\"up\">+4<\/nobr>","PLACE":59,"OLD":63,"NAME":"gimulti2","ALTSCORE":"6844","DIFF":"96%","TOTAL_SCORE":"7092","FLAG":"se","REGION_NAME":"J\u00f6nk\u00f6ping","TOTAL_TAKES":"31","UNIQUE_ZONES":"28","DISTANCE":"  0","DURATION":"0.0"},{"CHANGE":"<nobr class=\"down\">-4<\/nobr>","PLACE":60,"OLD":56,"NAME":"\u00c5hh\u00e5","ALTSCORE":"6034","DIFF":"60%","TOTAL_SCORE":"10052","FLAG":"se","REGION_NAME":"J\u00f6nk\u00f6ping","TOTAL_TAKES":"47","UNIQUE_ZONES":"18","DISTANCE":"  1","DURATION":"0.1"},{"CHANGE":"<nobr class=\"up\">+4<\/nobr>","PLACE":61,"OLD":65,"NAME":"Woodstock","ALTSCORE":"5890","DIFF":"86%","TOTAL_SCORE":"6835","FLAG":"se","REGION_NAME":"J\u00f6nk\u00f6ping","TOTAL_TAKES":"27","UNIQUE_ZONES":"24","DISTANCE":"  0","DURATION":"0.0"},{"CHANGE":"<nobr class=\"up\">+6<\/nobr>","PLACE":62,"OLD":68,"NAME":"WalterOrn","ALTSCORE":"5745","DIFF":"89%","TOTAL_SCORE":"6415","FLAG":"se","REGION_NAME":"J\u00f6nk\u00f6ping","TOTAL_TAKES":"28","UNIQUE_ZONES":"19","DISTANCE":"  9","DURATION":"2.2"},{"CHANGE":"<nobr class=\"down\">-6<\/nobr>","PLACE":63,"OLD":57,"NAME":"Pacman162","ALTSCORE":"5686","DIFF":"59%","TOTAL_SCORE":"9572","FLAG":"se","REGION_NAME":"J\u00f6nk\u00f6ping","TOTAL_TAKES":"52","UNIQUE_ZONES":"15","DISTANCE":"  0","DURATION":"0.0"},{"CHANGE":"<nobr class=\"up\">+6<\/nobr>","PLACE":64,"OLD":70,"NAME":"Cyaneus","ALTSCORE":"5643","DIFF":"96%","TOTAL_SCORE":"5822","FLAG":"se","REGION_NAME":"J\u00f6nk\u00f6ping","TOTAL_TAKES":"29","UNIQUE_ZONES":"22","DISTANCE":"  0","DURATION":"0.0"},{"CHANGE":"<nobr class=\"down\">-6<\/nobr>","PLACE":65,"OLD":59,"NAME":"jimggus","ALTSCORE":"5422","DIFF":"66%","TOTAL_SCORE":"8186","FLAG":"se","REGION_NAME":"J\u00f6nk\u00f6ping","TOTAL_TAKES":"41","UNIQUE_ZONES":"17","DISTANCE":"  0","DURATION":"0.2"},{"CHANGE":"<nobr class=\"up\">+3<\/nobr>","PLACE":66,"OLD":69,"NAME":"starious","ALTSCORE":"5375","DIFF":"91%","TOTAL_SCORE":"5904","FLAG":"se","REGION_NAME":"J\u00f6nk\u00f6ping","TOTAL_TAKES":"31","UNIQUE_ZONES":"19","DISTANCE":"  2","DURATION":"0.4"},{"CHANGE":"<nobr class=\"down\">-5<\/nobr>","PLACE":67,"OLD":62,"NAME":"Spethznaz","ALTSCORE":"5297","DIFF":"73%","TOTAL_SCORE":"7181","FLAG":"se","REGION_NAME":"J\u00f6nk\u00f6ping","TOTAL_TAKES":"42","UNIQUE_ZONES":"16","DISTANCE":"  0","DURATION":"0.0"},{"CHANGE":"<nobr class=\"down\">-8<\/nobr>","PLACE":68,"OLD":60,"NAME":"Pinecone23","ALTSCORE":"5222","DIFF":"65%","TOTAL_SCORE":"7986","FLAG":"se","REGION_NAME":"J\u00f6nk\u00f6ping","TOTAL_TAKES":"28","UNIQUE_ZONES":"20","DISTANCE":"  0","DURATION":"0.0"},{"CHANGE":"<nobr class=\"up\">+4<\/nobr>","PLACE":69,"OLD":73,"NAME":"Trazze","ALTSCORE":"5181","DIFF":"95%","TOTAL_SCORE":"5420","FLAG":"se","REGION_NAME":"J\u00f6nk\u00f6ping","TOTAL_TAKES":"27","UNIQUE_ZONES":"20","DISTANCE":"  0","DURATION":"0.1"},{"CHANGE":"<nobr class=\"up\">+9<\/nobr>","PLACE":70,"OLD":79,"NAME":"Flina","ALTSCORE":"5141","DIFF":"<nobr class=\"up\">107%<\/nobr>","TOTAL_SCORE":"4761","FLAG":"se","REGION_NAME":"J\u00f6nk\u00f6ping","TOTAL_TAKES":"23","UNIQUE_ZONES":"21","DISTANCE":"  7","DURATION":"1.5"},{"CHANGE":"<nobr class=\"up\">+5<\/nobr>","PLACE":71,"OLD":76,"NAME":"Thorre","ALTSCORE":"4819","DIFF":"93%","TOTAL_SCORE":"5162","FLAG":"se","REGION_NAME":"J\u00f6nk\u00f6ping","TOTAL_TAKES":"21","UNIQUE_ZONES":"20","DISTANCE":"  0","DURATION":"0.0"},{"CHANGE":"<nobr class=\"up\">+13<\/nobr>","PLACE":72,"OLD":85,"NAME":"Jeremia","ALTSCORE":"4819","DIFF":"<nobr class=\"up\">122%<\/nobr>","TOTAL_SCORE":"3934","FLAG":"se","REGION_NAME":"J\u00f6nk\u00f6ping","TOTAL_TAKES":"21","UNIQUE_ZONES":"20","DISTANCE":"  0","DURATION":"0.0"},{"CHANGE":"<nobr class=\"down\">-2<\/nobr>","PLACE":73,"OLD":71,"NAME":"Tekula-2","ALTSCORE":"4743","DIFF":"83%","TOTAL_SCORE":"5647","FLAG":"se","REGION_NAME":"J\u00f6nk\u00f6ping","TOTAL_TAKES":"26","UNIQUE_ZONES":"18","DISTANCE":"  0","DURATION":"0.0"},{"CHANGE":"<nobr class=\"up\">+7<\/nobr>","PLACE":74,"OLD":81,"NAME":"Anonymus1","ALTSCORE":"4686","DIFF":"<nobr class=\"up\">103%<\/nobr>","TOTAL_SCORE":"4523","FLAG":"se","REGION_NAME":"J\u00f6nk\u00f6ping","TOTAL_TAKES":"25","UNIQUE_ZONES":"18","DISTANCE":"  0","DURATION":"0.1"},{"CHANGE":"<nobr class=\"down\">-9<\/nobr>","PLACE":75,"OLD":66,"NAME":"VenaVena","ALTSCORE":"4436","DIFF":"67%","TOTAL_SCORE":"6533","FLAG":"se","REGION_NAME":"J\u00f6nk\u00f6ping","TOTAL_TAKES":"27","UNIQUE_ZONES":"16","DISTANCE":"  0","DURATION":"0.0"},{"CHANGE":"<nobr class=\"down\">-1<\/nobr>","PLACE":76,"OLD":75,"NAME":"iUserD33C3D0","ALTSCORE":"4196","DIFF":"80%","TOTAL_SCORE":"5218","FLAG":"se","REGION_NAME":"J\u00f6nk\u00f6ping","TOTAL_TAKES":"26","UNIQUE_ZONES":"15","DISTANCE":"  0","DURATION":"0.1"},{"CHANGE":"-","PLACE":77,"OLD":77,"NAME":"Smurfiz","ALTSCORE":"4048","DIFF":"79%","TOTAL_SCORE":"5077","FLAG":"se","REGION_NAME":"J\u00f6nk\u00f6ping","TOTAL_TAKES":"23","UNIQUE_ZONES":"15","DISTANCE":"  0","DURATION":"0.1"},{"CHANGE":"<nobr class=\"down\">-4<\/nobr>","PLACE":78,"OLD":74,"NAME":"astf7","ALTSCORE":"4033","DIFF":"74%","TOTAL_SCORE":"5393","FLAG":"se","REGION_NAME":"J\u00f6nk\u00f6ping","TOTAL_TAKES":"20","UNIQUE_ZONES":"16","DISTANCE":"  0","DURATION":"0.5"},{"CHANGE":"<nobr class=\"up\">+15<\/nobr>","PLACE":79,"OLD":94,"NAME":"ektr\u00e4d","ALTSCORE":"3976","DIFF":"<nobr class=\"up\">120%<\/nobr>","TOTAL_SCORE":"3310","FLAG":"se","REGION_NAME":"J\u00f6nk\u00f6ping","TOTAL_TAKES":"19","UNIQUE_ZONES":"16","DISTANCE":"  0","DURATION":"0.7"},{"CHANGE":"<nobr class=\"up\">+10<\/nobr>","PLACE":80,"OLD":90,"NAME":"Diamnat","ALTSCORE":"3803","DIFF":"<nobr class=\"up\">107%<\/nobr>","TOTAL_SCORE":"3545","FLAG":"se","REGION_NAME":"J\u00f6nk\u00f6ping","TOTAL_TAKES":"16","UNIQUE_ZONES":"16","DISTANCE":"  0","DURATION":"0.4"},{"CHANGE":"<nobr class=\"up\">+8<\/nobr>","PLACE":81,"OLD":89,"NAME":"gurra_gggg","ALTSCORE":"3678","DIFF":"<nobr class=\"up\">101%<\/nobr>","TOTAL_SCORE":"3630","FLAG":"se","REGION_NAME":"J\u00f6nk\u00f6ping","TOTAL_TAKES":"17","UNIQUE_ZONES":"15","DISTANCE":"  0","DURATION":"0.4"},{"CHANGE":"<nobr class=\"down\">-4<\/nobr>","PLACE":82,"OLD":78,"NAME":"Lemontrees","ALTSCORE":"3648","DIFF":"75%","TOTAL_SCORE":"4853","FLAG":"se","REGION_NAME":"J\u00f6nk\u00f6ping","TOTAL_TAKES":"26","UNIQUE_ZONES":"12","DISTANCE":"  0","DURATION":"0.0"},{"CHANGE":"<nobr class=\"up\">+8<\/nobr>","PLACE":83,"OLD":91,"NAME":"Sirirokitowicz","ALTSCORE":"3620","DIFF":"<nobr class=\"up\">107%<\/nobr>","TOTAL_SCORE":"3375","FLAG":"se","REGION_NAME":"J\u00f6nk\u00f6ping","TOTAL_TAKES":"16","UNIQUE_ZONES":"15","DISTANCE":"  0","DURATION":"0.5"},{"CHANGE":"<nobr class=\"up\">+12<\/nobr>","PLACE":84,"OLD":96,"NAME":"oltok","ALTSCORE":"3496","DIFF":"<nobr class=\"up\">108%<\/nobr>","TOTAL_SCORE":"3210","FLAG":"se","REGION_NAME":"J\u00f6nk\u00f6ping","TOTAL_TAKES":"17","UNIQUE_ZONES":"14","DISTANCE":"  0","DURATION":"0.0"},{"CHANGE":"<nobr class=\"down\">-2<\/nobr>","PLACE":85,"OLD":83,"NAME":"iceking3038","ALTSCORE":"3360","DIFF":"76%","TOTAL_SCORE":"4372","FLAG":"se","REGION_NAME":"J\u00f6nk\u00f6ping","TOTAL_TAKES":"21","UNIQUE_ZONES":"12","DISTANCE":"  0","DURATION":"0.2"},{"CHANGE":"<nobr class=\"up\">+6<\/nobr>","PLACE":86,"OLD":92,"NAME":"tulle","ALTSCORE":"3303","DIFF":"99%","TOTAL_SCORE":"3330","FLAG":"se","REGION_NAME":"J\u00f6nk\u00f6ping","TOTAL_TAKES":"20","UNIQUE_ZONES":"12","DISTANCE":"  0","DURATION":"0.0"},{"CHANGE":"<nobr class=\"down\">-15<\/nobr>","PLACE":87,"OLD":72,"NAME":"SweKen84","ALTSCORE":"3235","DIFF":"59%","TOTAL_SCORE":"5440","FLAG":"se","REGION_NAME":"J\u00f6nk\u00f6ping","TOTAL_TAKES":"22","UNIQUE_ZONES":"11","DISTANCE":"  0","DURATION":"0.0"},{"CHANGE":"<nobr class=\"down\">-1<\/nobr>","PLACE":88,"OLD":87,"NAME":"lindjack","ALTSCORE":"3072","DIFF":"80%","TOTAL_SCORE":"3810","FLAG":"se","REGION_NAME":"J\u00f6nk\u00f6ping","TOTAL_TAKES":"16","UNIQUE_ZONES":"12","DISTANCE":"  0","DURATION":"0.0"},{"CHANGE":"<nobr class=\"down\">-5<\/nobr>","PLACE":89,"OLD":84,"NAME":"kiek","ALTSCORE":"3004","DIFF":"71%","TOTAL_SCORE":"4223","FLAG":"se","REGION_NAME":"J\u00f6nk\u00f6ping","TOTAL_TAKES":"18","UNIQUE_ZONES":"11","DISTANCE":"  0","DURATION":"0.4"},{"CHANGE":"<nobr class=\"up\">+15<\/nobr>","PLACE":90,"OLD":105,"NAME":"CatLover33","ALTSCORE":"2832","DIFF":"<nobr class=\"up\">100%<\/nobr>","TOTAL_SCORE":"2818","FLAG":"se","REGION_NAME":"J\u00f6nk\u00f6ping","TOTAL_TAKES":"15","UNIQUE_ZONES":"11","DISTANCE":"  0","DURATION":"0.5"},{"CHANGE":"<nobr class=\"up\">+21<\/nobr>","PLACE":91,"OLD":112,"NAME":"alicmeli","ALTSCORE":"2774","DIFF":"<nobr class=\"up\">110%<\/nobr>","TOTAL_SCORE":"2519","FLAG":"se","REGION_NAME":"J\u00f6nk\u00f6ping","TOTAL_TAKES":"14","UNIQUE_ZONES":"11","DISTANCE":"  0","DURATION":"0.5"},{"CHANGE":"<nobr class=\"up\">+15<\/nobr>","PLACE":92,"OLD":107,"NAME":"Love_11","ALTSCORE":"2774","DIFF":"98%","TOTAL_SCORE":"2805","FLAG":"se","REGION_NAME":"J\u00f6nk\u00f6ping","TOTAL_TAKES":"14","UNIQUE_ZONES":"11","DISTANCE":"  0","DURATION":"0.6"},{"CHANGE":"<nobr class=\"down\">-11<\/nobr>","PLACE":93,"OLD":82,"NAME":"anoh","ALTSCORE":"2716","DIFF":"61%","TOTAL_SCORE":"4396","FLAG":"se","REGION_NAME":"J\u00f6nk\u00f6ping","TOTAL_TAKES":"13","UNIQUE_ZONES":"11","DISTANCE":"  0","DURATION":"0.0"},{"CHANGE":"<nobr class=\"up\">+15<\/nobr>","PLACE":94,"OLD":109,"NAME":"Stella11","ALTSCORE":"2716","DIFF":"<nobr class=\"up\">101%<\/nobr>","TOTAL_SCORE":"2681","FLAG":"se","REGION_NAME":"J\u00f6nk\u00f6ping","TOTAL_TAKES":"13","UNIQUE_ZONES":"11","DISTANCE":"  0","DURATION":"0.4"},{"CHANGE":"<nobr class=\"up\">+16<\/nobr>","PLACE":95,"OLD":111,"NAME":"Alesjandro","ALTSCORE":"2716","DIFF":"<nobr class=\"up\">104%<\/nobr>","TOTAL_SCORE":"2598","FLAG":"se","REGION_NAME":"J\u00f6nk\u00f6ping","TOTAL_TAKES":"13","UNIQUE_ZONES":"11","DISTANCE":"  0","DURATION":"0.6"},{"CHANGE":"<nobr class=\"up\">+17<\/nobr>","PLACE":96,"OLD":113,"NAME":"Zappa","ALTSCORE":"2659","DIFF":"<nobr class=\"up\">106%<\/nobr>","TOTAL_SCORE":"2495","FLAG":"se","REGION_NAME":"J\u00f6nk\u00f6ping","TOTAL_TAKES":"12","UNIQUE_ZONES":"11","DISTANCE":"  0","DURATION":"0.0"},{"CHANGE":"<nobr class=\"up\">+28<\/nobr>","PLACE":97,"OLD":125,"NAME":"Liacha","ALTSCORE":"2659","DIFF":"<nobr class=\"up\">128%<\/nobr>","TOTAL_SCORE":"2076","FLAG":"se","REGION_NAME":"J\u00f6nk\u00f6ping","TOTAL_TAKES":"12","UNIQUE_ZONES":"11","DISTANCE":"  0","DURATION":"0.6"},{"CHANGE":"<nobr class=\"up\">+24<\/nobr>","PLACE":98,"OLD":122,"NAME":"marabou\u00e4rgott","ALTSCORE":"2659","DIFF":"<nobr class=\"up\">117%<\/nobr>","TOTAL_SCORE":"2261","FLAG":"se","REGION_NAME":"J\u00f6nk\u00f6ping","TOTAL_TAKES":"12","UNIQUE_ZONES":"11","DISTANCE":"  0","DURATION":"0.4"},{"CHANGE":"<nobr class=\"down\">-32<\/nobr>","PLACE":99,"OLD":67,"NAME":"basketfigge","ALTSCORE":"2649","DIFF":"41%","TOTAL_SCORE":"6436","FLAG":"se","REGION_NAME":"J\u00f6nk\u00f6ping","TOTAL_TAKES":"31","UNIQUE_ZONES":"5","DISTANCE":"  0","DURATION":"0.0"},{"CHANGE":"<nobr class=\"up\">+24<\/nobr>","PLACE":100,"OLD":124,"NAME":"r\u00f6vdahl","ALTSCORE":"2601","DIFF":"<nobr class=\"up\">122%<\/nobr>","TOTAL_SCORE":"2123","FLAG":"se","REGION_NAME":"J\u00f6nk\u00f6ping","TOTAL_TAKES":"11","UNIQUE_ZONES":"11","DISTANCE":"  0","DURATION":"0.0"},{"CHANGE":"<nobr class=\"up\">+1<\/nobr>","PLACE":101,"OLD":102,"NAME":"HLHabooks","ALTSCORE":"2570","DIFF":"90%","TOTAL_SCORE":"2845","FLAG":"se","REGION_NAME":"J\u00f6nk\u00f6ping","TOTAL_TAKES":"13","UNIQUE_ZONES":"10","DISTANCE":"  0","DURATION":"0.0"},{"CHANGE":"<nobr class=\"up\">+12<\/nobr>","PLACE":102,"OLD":114,"NAME":"babbelabbe","ALTSCORE":"2533","DIFF":"<nobr class=\"up\">102%<\/nobr>","TOTAL_SCORE":"2476","FLAG":"se","REGION_NAME":"J\u00f6nk\u00f6ping","TOTAL_TAKES":"13","UNIQUE_ZONES":"10","DISTANCE":"  0","DURATION":"0.5"},{"CHANGE":"<nobr class=\"up\">+14<\/nobr>","PLACE":103,"OLD":117,"NAME":"MrBo","ALTSCORE":"2475","DIFF":"<nobr class=\"up\">106%<\/nobr>","TOTAL_SCORE":"2318","FLAG":"se","REGION_NAME":"J\u00f6nk\u00f6ping","TOTAL_TAKES":"12","UNIQUE_ZONES":"10","DISTANCE":"  0","DURATION":"0.6"},{"CHANGE":"<nobr class=\"up\">+12<\/nobr>","PLACE":104,"OLD":116,"NAME":"Salami_o_bacon","ALTSCORE":"2475","DIFF":"<nobr class=\"up\">105%<\/nobr>","TOTAL_SCORE":"2344","FLAG":"se","REGION_NAME":"J\u00f6nk\u00f6ping","TOTAL_TAKES":"12","UNIQUE_ZONES":"10","DISTANCE":"  0","DURATION":"0.0"},{"CHANGE":"<nobr class=\"down\">-25<\/nobr>","PLACE":105,"OLD":80,"NAME":"Sopel","ALTSCORE":"2454","DIFF":"51%","TOTAL_SCORE":"4745","FLAG":"se","REGION_NAME":"J\u00f6nk\u00f6ping","TOTAL_TAKES":"18","UNIQUE_ZONES":"8","DISTANCE":"  0","DURATION":"0.0"},{"CHANGE":"<nobr class=\"down\">-5<\/nobr>","PLACE":106,"OLD":101,"NAME":"Polar","ALTSCORE":"2350","DIFF":"79%","TOTAL_SCORE":"2966","FLAG":"se","REGION_NAME":"J\u00f6nk\u00f6ping","TOTAL_TAKES":"13","UNIQUE_ZONES":"9","DISTANCE":"  0","DURATION":"0.5"},{"CHANGE":"<nobr class=\"up\">+14<\/nobr>","PLACE":107,"OLD":121,"NAME":"wilhelmhej","ALTSCORE":"2292","DIFF":"<nobr class=\"up\">100%<\/nobr>","TOTAL_SCORE":"2279","FLAG":"se","REGION_NAME":"J\u00f6nk\u00f6ping","TOTAL_TAKES":"12","UNIQUE_ZONES":"9","DISTANCE":"  0","DURATION":"0.4"},{"CHANGE":"<nobr class=\"down\">-22<\/nobr>","PLACE":108,"OLD":86,"NAME":"964Porsche","ALTSCORE":"1993","DIFF":"52%","TOTAL_SCORE":"3824","FLAG":"se","REGION_NAME":"J\u00f6nk\u00f6ping","TOTAL_TAKES":"15","UNIQUE_ZONES":"6","DISTANCE":"  1","DURATION":"0.4"},{"CHANGE":"<nobr class=\"up\">+10<\/nobr>","PLACE":109,"OLD":119,"NAME":"malha","ALTSCORE":"1873","DIFF":"81%","TOTAL_SCORE":"2303","FLAG":"se","REGION_NAME":"J\u00f6nk\u00f6ping","TOTAL_TAKES":"10","UNIQUE_ZONES":"6","DISTANCE":"  3","DURATION":"0.9"},{"CHANGE":"<nobr class=\"down\">-17<\/nobr>","PLACE":110,"OLD":93,"NAME":"lillm\u00f6rten","ALTSCORE":"1743","DIFF":"52%","TOTAL_SCORE":"3329","FLAG":"se","REGION_NAME":"J\u00f6nk\u00f6ping","TOTAL_TAKES":"10","UNIQUE_ZONES":"6","DISTANCE":"  2","DURATION":"0.1"},{"CHANGE":"<nobr class=\"down\">-7<\/nobr>","PLACE":111,"OLD":104,"NAME":"mandorfxx","ALTSCORE":"1672","DIFF":"58%","TOTAL_SCORE":"2835","FLAG":"se","REGION_NAME":"J\u00f6nk\u00f6ping","TOTAL_TAKES":"14","UNIQUE_ZONES":"5","DISTANCE":"  0","DURATION":"0.0"},{"CHANGE":"<nobr class=\"up\">+25<\/nobr>","PLACE":112,"OLD":137,"NAME":"TheGoatLeo23","ALTSCORE":"1626","DIFF":"<nobr class=\"up\">100%<\/nobr>","TOTAL_SCORE":"1626","FLAG":"se","REGION_NAME":"J\u00f6nk\u00f6ping","TOTAL_TAKES":"10","UNIQUE_ZONES":"6","DISTANCE":"  0","DURATION":"0.0"},{"CHANGE":"<nobr class=\"down\">-18<\/nobr>","PLACE":113,"OLD":95,"NAME":"eunsson","ALTSCORE":"1626","DIFF":"49%","TOTAL_SCORE":"3284","FLAG":"se","REGION_NAME":"J\u00f6nk\u00f6ping","TOTAL_TAKES":"10","UNIQUE_ZONES":"6","DISTANCE":"  0","DURATION":"0.0"},{"CHANGE":"<nobr class=\"up\">+12<\/nobr>","PLACE":114,"OLD":126,"NAME":"ColinLeo","ALTSCORE":"1626","DIFF":"80%","TOTAL_SCORE":"2018","FLAG":"se","REGION_NAME":"J\u00f6nk\u00f6ping","TOTAL_TAKES":"10","UNIQUE_ZONES":"6","DISTANCE":"  0","DURATION":"0.0"},{"CHANGE":"<nobr class=\"up\">+16<\/nobr>","PLACE":115,"OLD":131,"NAME":"mannequin","ALTSCORE":"1626","DIFF":"86%","TOTAL_SCORE":"1870","FLAG":"se","REGION_NAME":"J\u00f6nk\u00f6ping","TOTAL_TAKES":"10","UNIQUE_ZONES":"6","DISTANCE":"  0","DURATION":"0.0"},{"CHANGE":"<nobr class=\"up\">+17<\/nobr>","PLACE":116,"OLD":133,"NAME":"Thelander456","ALTSCORE":"1626","DIFF":"90%","TOTAL_SCORE":"1795","FLAG":"se","REGION_NAME":"J\u00f6nk\u00f6ping","TOTAL_TAKES":"10","UNIQUE_ZONES":"6","DISTANCE":"  0","DURATION":"0.0"},{"CHANGE":"<nobr class=\"up\">+24<\/nobr>","PLACE":117,"OLD":141,"NAME":"Alwin.11D","ALTSCORE":"1568","DIFF":"<nobr class=\"up\">100%<\/nobr>","TOTAL_SCORE":"1562","FLAG":"se","REGION_NAME":"J\u00f6nk\u00f6ping","TOTAL_TAKES":"9","UNIQUE_ZONES":"6","DISTANCE":"  0","DURATION":"0.4"},{"CHANGE":"<nobr class=\"down\">-18<\/nobr>","PLACE":118,"OLD":100,"NAME":"Rezin","ALTSCORE":"1568","DIFF":"52%","TOTAL_SCORE":"3004","FLAG":"se","REGION_NAME":"J\u00f6nk\u00f6ping","TOTAL_TAKES":"9","UNIQUE_ZONES":"6","DISTANCE":"  0","DURATION":"0.0"},{"CHANGE":"<nobr class=\"up\">+9<\/nobr>","PLACE":119,"OLD":128,"NAME":"Raznipriv","ALTSCORE":"1568","DIFF":"80%","TOTAL_SCORE":"1958","FLAG":"se","REGION_NAME":"J\u00f6nk\u00f6ping","TOTAL_TAKES":"9","UNIQUE_ZONES":"6","DISTANCE":"  0","DURATION":"0.0"},{"CHANGE":"<nobr class=\"down\">-22<\/nobr>","PLACE":120,"OLD":98,"NAME":"SweNerd84","ALTSCORE":"1552","DIFF":"48%","TOTAL_SCORE":"3172","FLAG":"se","REGION_NAME":"J\u00f6nk\u00f6ping","TOTAL_TAKES":"8","UNIQUE_ZONES":"6","DISTANCE":"  3","DURATION":"1.5"},{"CHANGE":"<nobr class=\"down\">-22<\/nobr>","PLACE":121,"OLD":99,"NAME":"chuck","ALTSCORE":"1546","DIFF":"49%","TOTAL_SCORE":"3100","FLAG":"se","REGION_NAME":"J\u00f6nk\u00f6ping","TOTAL_TAKES":"15","UNIQUE_ZONES":"4","DISTANCE":"  0","DURATION":"0.5"},{"CHANGE":"<nobr class=\"up\">+26<\/nobr>","PLACE":122,"OLD":148,"NAME":"ballerinas_2","ALTSCORE":"1510","DIFF":"<nobr class=\"up\">109%<\/nobr>","TOTAL_SCORE":"1373","FLAG":"se","REGION_NAME":"J\u00f6nk\u00f6ping","TOTAL_TAKES":"8","UNIQUE_ZONES":"6","DISTANCE":"  0","DURATION":"0.0"},{"CHANGE":"<nobr class=\"down\">-8<\/nobr>","PLACE":123,"OLD":115,"NAME":"Farmor54","ALTSCORE":"1510","DIFF":"62%","TOTAL_SCORE":"2409","FLAG":"se","REGION_NAME":"J\u00f6nk\u00f6ping","TOTAL_TAKES":"7","UNIQUE_ZONES":"6","DISTANCE":"  1","DURATION":"0.4"},{"CHANGE":"<nobr class=\"up\">+18<\/nobr>","PLACE":124,"OLD":142,"NAME":"AfitRycken","ALTSCORE":"1510","DIFF":"96%","TOTAL_SCORE":"1557","FLAG":"se","REGION_NAME":"J\u00f6nk\u00f6ping","TOTAL_TAKES":"8","UNIQUE_ZONES":"6","DISTANCE":"  0","DURATION":"0.6"},{"CHANGE":"<nobr class=\"up\">+10<\/nobr>","PLACE":125,"OLD":135,"NAME":"Vatikanstaten","ALTSCORE":"1510","DIFF":"90%","TOTAL_SCORE":"1662","FLAG":"se","REGION_NAME":"J\u00f6nk\u00f6ping","TOTAL_TAKES":"8","UNIQUE_ZONES":"6","DISTANCE":"  0","DURATION":"0.0"},{"CHANGE":"<nobr class=\"up\">+10<\/nobr>","PLACE":126,"OLD":136,"NAME":"Ida_11","ALTSCORE":"1510","DIFF":"92%","TOTAL_SCORE":"1628","FLAG":"se","REGION_NAME":"J\u00f6nk\u00f6ping","TOTAL_TAKES":"8","UNIQUE_ZONES":"6","DISTANCE":"  0","DURATION":"0.5"},{"CHANGE":"<nobr class=\"down\">-24<\/nobr>","PLACE":127,"OLD":103,"NAME":"timjan60","ALTSCORE":"1453","DIFF":"51%","TOTAL_SCORE":"2837","FLAG":"se","REGION_NAME":"J\u00f6nk\u00f6ping","TOTAL_TAKES":"7","UNIQUE_ZONES":"6","DISTANCE":"  0","DURATION":"0.0"},{"CHANGE":"<nobr class=\"up\">+16<\/nobr>","PLACE":128,"OLD":144,"NAME":"AlvinBergman","ALTSCORE":"1453","DIFF":"<nobr class=\"up\">100%<\/nobr>","TOTAL_SCORE":"1448","FLAG":"se","REGION_NAME":"J\u00f6nk\u00f6ping","TOTAL_TAKES":"7","UNIQUE_ZONES":"6","DISTANCE":"  0","DURATION":"0.6"},{"CHANGE":"<nobr class=\"up\">+20<\/nobr>","PLACE":129,"OLD":149,"NAME":"lararutmaja","ALTSCORE":"1453","DIFF":"<nobr class=\"up\">106%<\/nobr>","TOTAL_SCORE":"1366","FLAG":"se","REGION_NAME":"J\u00f6nk\u00f6ping","TOTAL_TAKES":"7","UNIQUE_ZONES":"6","DISTANCE":"  0","DURATION":"0.0"},{"CHANGE":"<nobr class=\"up\">+21<\/nobr>","PLACE":130,"OLD":151,"NAME":"Krasniqiii","ALTSCORE":"1453","DIFF":"<nobr class=\"up\">111%<\/nobr>","TOTAL_SCORE":"1309","FLAG":"se","REGION_NAME":"J\u00f6nk\u00f6ping","TOTAL_TAKES":"7","UNIQUE_ZONES":"6","DISTANCE":"  0","DURATION":"0.4"},{"CHANGE":"<nobr class=\"up\">+25<\/nobr>","PLACE":131,"OLD":156,"NAME":"gabbee","ALTSCORE":"1453","DIFF":"<nobr class=\"up\">113%<\/nobr>","TOTAL_SCORE":"1280","FLAG":"se","REGION_NAME":"J\u00f6nk\u00f6ping","TOTAL_TAKES":"7","UNIQUE_ZONES":"6","DISTANCE":"  0","DURATION":"0.0"},{"CHANGE":"<nobr class=\"up\">+8<\/nobr>","PLACE":132,"OLD":140,"NAME":"Elosten","ALTSCORE":"1453","DIFF":"91%","TOTAL_SCORE":"1592","FLAG":"se","REGION_NAME":"J\u00f6nk\u00f6ping","TOTAL_TAKES":"7","UNIQUE_ZONES":"6","DISTANCE":"  0","DURATION":"0.4"},{"CHANGE":"<nobr class=\"up\">+28<\/nobr>","PLACE":133,"OLD":161,"NAME":"meyapeya","ALTSCORE":"1453","DIFF":"<nobr class=\"up\">119%<\/nobr>","TOTAL_SCORE":"1218","FLAG":"se","REGION_NAME":"J\u00f6nk\u00f6ping","TOTAL_TAKES":"7","UNIQUE_ZONES":"6","DISTANCE":"  0","DURATION":"0.4"},{"CHANGE":"<nobr class=\"down\">-37<\/nobr>","PLACE":134,"OLD":97,"NAME":"sagayderman","ALTSCORE":"1442","DIFF":"45%","TOTAL_SCORE":"3178","FLAG":"se","REGION_NAME":"J\u00f6nk\u00f6ping","TOTAL_TAKES":"10","UNIQUE_ZONES":"5","DISTANCE":"  0","DURATION":"0.0"},{"CHANGE":"<nobr class=\"down\">-27<\/nobr>","PLACE":135,"OLD":108,"NAME":"IA19","ALTSCORE":"1442","DIFF":"52%","TOTAL_SCORE":"2742","FLAG":"se","REGION_NAME":"J\u00f6nk\u00f6ping","TOTAL_TAKES":"10","UNIQUE_ZONES":"5","DISTANCE":"  0","DURATION":"0.0"},{"CHANGE":"<nobr class=\"up\">+27<\/nobr>","PLACE":136,"OLD":163,"NAME":"Meduza3","ALTSCORE":"1395","DIFF":"<nobr class=\"up\">116%<\/nobr>","TOTAL_SCORE":"1199","FLAG":"se","REGION_NAME":"J\u00f6nk\u00f6ping","TOTAL_TAKES":"6","UNIQUE_ZONES":"6","DISTANCE":"  0","DURATION":"0.4"},{"CHANGE":"<nobr class=\"up\">+18<\/nobr>","PLACE":137,"OLD":155,"NAME":"nyg\u00e5rd11","ALTSCORE":"1395","DIFF":"<nobr class=\"up\">108%<\/nobr>","TOTAL_SCORE":"1286","FLAG":"se","REGION_NAME":"J\u00f6nk\u00f6ping","TOTAL_TAKES":"6","UNIQUE_ZONES":"6","DISTANCE":"  0","DURATION":"0.0"},{"CHANGE":"<nobr class=\"up\">+27<\/nobr>","PLACE":138,"OLD":165,"NAME":"Dallsten","ALTSCORE":"1395","DIFF":"<nobr class=\"up\">120%<\/nobr>","TOTAL_SCORE":"1156","FLAG":"se","REGION_NAME":"J\u00f6nk\u00f6ping","TOTAL_TAKES":"6","UNIQUE_ZONES":"6","DISTANCE":"  0","DURATION":"0.0"},{"CHANGE":"<nobr class=\"up\">+15<\/nobr>","PLACE":139,"OLD":154,"NAME":"EEL4813","ALTSCORE":"1395","DIFF":"<nobr class=\"up\">107%<\/nobr>","TOTAL_SCORE":"1297","FLAG":"se","REGION_NAME":"J\u00f6nk\u00f6ping","TOTAL_TAKES":"6","UNIQUE_ZONES":"6","DISTANCE":"  0","DURATION":"0.0"},{"CHANGE":"<nobr class=\"up\">+32<\/nobr>","PLACE":140,"OLD":172,"NAME":"deregnarguzzar","ALTSCORE":"1395","DIFF":"<nobr class=\"up\">137%<\/nobr>","TOTAL_SCORE":"1016","FLAG":"se","REGION_NAME":"J\u00f6nk\u00f6ping","TOTAL_TAKES":"6","UNIQUE_ZONES":"6","DISTANCE":"  0","DURATION":"0.0"},{"CHANGE":"<nobr class=\"up\">+6<\/nobr>","PLACE":141,"OLD":147,"NAME":"theohovde","ALTSCORE":"1395","DIFF":"98%","TOTAL_SCORE":"1418","FLAG":"se","REGION_NAME":"J\u00f6nk\u00f6ping","TOTAL_TAKES":"6","UNIQUE_ZONES":"6","DISTANCE":"  0","DURATION":"0.0"},{"CHANGE":"<nobr class=\"up\">+26<\/nobr>","PLACE":142,"OLD":168,"NAME":"Anisdonrasmus","ALTSCORE":"1395","DIFF":"<nobr class=\"up\">126%<\/nobr>","TOTAL_SCORE":"1103","FLAG":"se","REGION_NAME":"J\u00f6nk\u00f6ping","TOTAL_TAKES":"6","UNIQUE_ZONES":"6","DISTANCE":"  0","DURATION":"0.3"},{"CHANGE":"<nobr class=\"up\">+21<\/nobr>","PLACE":143,"OLD":164,"NAME":"ApaOrangutang","ALTSCORE":"1395","DIFF":"<nobr class=\"up\">119%<\/nobr>","TOTAL_SCORE":"1164","FLAG":"se","REGION_NAME":"J\u00f6nk\u00f6ping","TOTAL_TAKES":"6","UNIQUE_ZONES":"6","DISTANCE":"  0","DURATION":"0.0"},{"CHANGE":"<nobr class=\"up\">+14<\/nobr>","PLACE":144,"OLD":158,"NAME":"Moondancer","ALTSCORE":"1395","DIFF":"<nobr class=\"up\">110%<\/nobr>","TOTAL_SCORE":"1260","FLAG":"se","REGION_NAME":"J\u00f6nk\u00f6ping","TOTAL_TAKES":"6","UNIQUE_ZONES":"6","DISTANCE":"  0","DURATION":"0.0"},{"CHANGE":"<nobr class=\"up\">+21<\/nobr>","PLACE":145,"OLD":166,"NAME":"DijonSenap","ALTSCORE":"1395","DIFF":"<nobr class=\"up\">121%<\/nobr>","TOTAL_SCORE":"1146","FLAG":"se","REGION_NAME":"J\u00f6nk\u00f6ping","TOTAL_TAKES":"6","UNIQUE_ZONES":"6","DISTANCE":"  0","DURATION":"0.4"},{"CHANGE":"<nobr class=\"up\">+14<\/nobr>","PLACE":146,"OLD":160,"NAME":"ECK","ALTSCORE":"1395","DIFF":"<nobr class=\"up\">113%<\/nobr>","TOTAL_SCORE":"1225","FLAG":"se","REGION_NAME":"J\u00f6nk\u00f6ping","TOTAL_TAKES":"6","UNIQUE_ZONES":"6","DISTANCE":"  0","DURATION":"0.0"},{"CHANGE":"<nobr class=\"down\">-59<\/nobr>","PLACE":147,"OLD":88,"NAME":"gotland003","ALTSCORE":"1384","DIFF":"37%","TOTAL_SCORE":"3651","FLAG":"se","REGION_NAME":"J\u00f6nk\u00f6ping","TOTAL_TAKES":"9","UNIQUE_ZONES":"5","DISTANCE":"  0","DURATION":"0.0"},{"CHANGE":"<nobr class=\"down\">-16<\/nobr>","PLACE":148,"OLD":132,"NAME":"pilen","ALTSCORE":"1384","DIFF":"74%","TOTAL_SCORE":"1858","FLAG":"se","REGION_NAME":"J\u00f6nk\u00f6ping","TOTAL_TAKES":"9","UNIQUE_ZONES":"5","DISTANCE":"  0","DURATION":"0.0"},{"CHANGE":"<nobr class=\"down\">-19<\/nobr>","PLACE":149,"OLD":130,"NAME":"Olvert","ALTSCORE":"1384","DIFF":"73%","TOTAL_SCORE":"1881","FLAG":"se","REGION_NAME":"J\u00f6nk\u00f6ping","TOTAL_TAKES":"9","UNIQUE_ZONES":"5","DISTANCE":"  0","DURATION":"0.0"},{"CHANGE":"<nobr class=\"down\">-30<\/nobr>","PLACE":150,"OLD":120,"NAME":"mammakanin","ALTSCORE":"1384","DIFF":"60%","TOTAL_SCORE":"2295","FLAG":"se","REGION_NAME":"J\u00f6nk\u00f6ping","TOTAL_TAKES":"9","UNIQUE_ZONES":"5","DISTANCE":"  0","DURATION":"0.0"},{"CHANGE":"<nobr class=\"down\">-45<\/nobr>","PLACE":151,"OLD":106,"NAME":"leobac","ALTSCORE":"1384","DIFF":"49%","TOTAL_SCORE":"2805","FLAG":"se","REGION_NAME":"J\u00f6nk\u00f6ping","TOTAL_TAKES":"9","UNIQUE_ZONES":"5","DISTANCE":"  0","DURATION":"0.0"},{"CHANGE":"<nobr class=\"down\">-29<\/nobr>","PLACE":152,"OLD":123,"NAME":"JPG","ALTSCORE":"1326","DIFF":"61%","TOTAL_SCORE":"2171","FLAG":"se","REGION_NAME":"J\u00f6nk\u00f6ping","TOTAL_TAKES":"8","UNIQUE_ZONES":"5","DISTANCE":"  0","DURATION":"0.0"},{"CHANGE":"<nobr class=\"up\">+4<\/nobr>","PLACE":153,"OLD":157,"NAME":"Muhammad1120","ALTSCORE":"1269","DIFF":"<nobr class=\"up\">100%<\/nobr>","TOTAL_SCORE":"1267","FLAG":"se","REGION_NAME":"J\u00f6nk\u00f6ping","TOTAL_TAKES":"7","UNIQUE_ZONES":"5","DISTANCE":"  0","DURATION":"0.4"},{"CHANGE":"<nobr class=\"down\">-9<\/nobr>","PLACE":154,"OLD":145,"NAME":"sivanhify","ALTSCORE":"1269","DIFF":"87%","TOTAL_SCORE":"1448","FLAG":"se","REGION_NAME":"J\u00f6nk\u00f6ping","TOTAL_TAKES":"7","UNIQUE_ZONES":"5","DISTANCE":"  0","DURATION":"0.0"},{"CHANGE":"<nobr class=\"down\">-45<\/nobr>","PLACE":155,"OLD":110,"NAME":"FreddanS","ALTSCORE":"1258","DIFF":"48%","TOTAL_SCORE":"2603","FLAG":"se","REGION_NAME":"J\u00f6nk\u00f6ping","TOTAL_TAKES":"10","UNIQUE_ZONES":"4","DISTANCE":"  0","DURATION":"0.0"},{"CHANGE":"<nobr class=\"down\">-22<\/nobr>","PLACE":156,"OLD":134,"NAME":"CplHicks","ALTSCORE":"1258","DIFF":"75%","TOTAL_SCORE":"1664","FLAG":"se","REGION_NAME":"J\u00f6nk\u00f6ping","TOTAL_TAKES":"10","UNIQUE_ZONES":"4","DISTANCE":"  0","DURATION":"0.0"},{"CHANGE":"<nobr class=\"down\">-39<\/nobr>","PLACE":157,"OLD":118,"NAME":"biggebank","ALTSCORE":"1246","DIFF":"53%","TOTAL_SCORE":"2310","FLAG":"se","REGION_NAME":"J\u00f6nk\u00f6ping","TOTAL_TAKES":"13","UNIQUE_ZONES":"3","DISTANCE":"  0","DURATION":"0.0"},{"CHANGE":"<nobr class=\"up\">+9<\/nobr>","PLACE":158,"OLD":167,"NAME":"fluffyunicron","ALTSCORE":"1211","DIFF":"<nobr class=\"up\">105%<\/nobr>","TOTAL_SCORE":"1144","FLAG":"se","REGION_NAME":"J\u00f6nk\u00f6ping","TOTAL_TAKES":"6","UNIQUE_ZONES":"5","DISTANCE":"  0","DURATION":"0.3"},{"CHANGE":"<nobr class=\"down\">-9<\/nobr>","PLACE":159,"OLD":150,"NAME":"HeddaFellman","ALTSCORE":"1211","DIFF":"91%","TOTAL_SCORE":"1322","FLAG":"se","REGION_NAME":"J\u00f6nk\u00f6ping","TOTAL_TAKES":"6","UNIQUE_ZONES":"5","DISTANCE":"  0","DURATION":"0.0"},{"CHANGE":"<nobr class=\"up\">+2<\/nobr>","PLACE":160,"OLD":162,"NAME":"Zodiac","ALTSCORE":"1142","DIFF":"94%","TOTAL_SCORE":"1210","FLAG":"se","REGION_NAME":"J\u00f6nk\u00f6ping","TOTAL_TAKES":"8","UNIQUE_ZONES":"4","DISTANCE":"  0","DURATION":"0.0"},{"CHANGE":"<nobr class=\"down\">-32<\/nobr>","PLACE":161,"OLD":129,"NAME":"styra","ALTSCORE":"1142","DIFF":"58%","TOTAL_SCORE":"1941","FLAG":"se","REGION_NAME":"J\u00f6nk\u00f6ping","TOTAL_TAKES":"8","UNIQUE_ZONES":"4","DISTANCE":"  0","DURATION":"0.0"},{"CHANGE":"<nobr class=\"down\">-35<\/nobr>","PLACE":162,"OLD":127,"NAME":"heax79","ALTSCORE":"1131","DIFF":"57%","TOTAL_SCORE":"1972","FLAG":"se","REGION_NAME":"J\u00f6nk\u00f6ping","TOTAL_TAKES":"11","UNIQUE_ZONES":"3","DISTANCE":"  0","DURATION":"0.0"},{"CHANGE":"<nobr class=\"down\">-24<\/nobr>","PLACE":163,"OLD":139,"NAME":"svart\u00e5n","ALTSCORE":"1085","DIFF":"67%","TOTAL_SCORE":"1611","FLAG":"se","REGION_NAME":"J\u00f6nk\u00f6ping","TOTAL_TAKES":"7","UNIQUE_ZONES":"4","DISTANCE":"  0","DURATION":"0.0"},{"CHANGE":"<nobr class=\"down\">-18<\/nobr>","PLACE":164,"OLD":146,"NAME":"DonKiwin","ALTSCORE":"1027","DIFF":"72%","TOTAL_SCORE":"1424","FLAG":"se","REGION_NAME":"J\u00f6nk\u00f6ping","TOTAL_TAKES":"6","UNIQUE_ZONES":"4","DISTANCE":"  0","DURATION":"0.3"},{"CHANGE":"<nobr class=\"up\">+5<\/nobr>","PLACE":165,"OLD":170,"NAME":"pegging","ALTSCORE":"416","DIFF":"38%","TOTAL_SCORE":"1067","FLAG":"se","REGION_NAME":"J\u00f6nk\u00f6ping","TOTAL_TAKES":"5","UNIQUE_ZONES":"1","DISTANCE":"  0","DURATION":"0.0"},{"CHANGE":"<nobr class=\"up\">+10<\/nobr>","PLACE":166,"OLD":176,"NAME":"Tova.Evelina","ALTSCORE":"416","DIFF":"42%","TOTAL_SCORE":"979","FLAG":"se","REGION_NAME":"J\u00f6nk\u00f6ping","TOTAL_TAKES":"5","UNIQUE_ZONES":"1","DISTANCE":"  0","DURATION":"0.0"},{"CHANGE":"<nobr class=\"up\">+2<\/nobr>","PLACE":167,"OLD":169,"NAME":"jeffne","ALTSCORE":"416","DIFF":"38%","TOTAL_SCORE":"1079","FLAG":"se","REGION_NAME":"J\u00f6nk\u00f6ping","TOTAL_TAKES":"5","UNIQUE_ZONES":"1","DISTANCE":"  0","DURATION":"0.0"},{"CHANGE":"<nobr class=\"up\">+11<\/nobr>","PLACE":168,"OLD":179,"NAME":"Seafi","ALTSCORE":"358","DIFF":"38%","TOTAL_SCORE":"940","FLAG":"se","REGION_NAME":"J\u00f6nk\u00f6ping","TOTAL_TAKES":"4","UNIQUE_ZONES":"1","DISTANCE":"  0","DURATION":"0.0"},{"CHANGE":"<nobr class=\"down\">-17<\/nobr>","PLACE":169,"OLD":152,"NAME":"Cobranos1234","ALTSCORE":"358","DIFF":"27%","TOTAL_SCORE":"1303","FLAG":"se","REGION_NAME":"J\u00f6nk\u00f6ping","TOTAL_TAKES":"4","UNIQUE_ZONES":"1","DISTANCE":"  0","DURATION":"0.0"},{"CHANGE":"<nobr class=\"up\">+7<\/nobr>","PLACE":170,"OLD":177,"NAME":"McAsterix","ALTSCORE":"358","DIFF":"36%","TOTAL_SCORE":"976","FLAG":"se","REGION_NAME":"J\u00f6nk\u00f6ping","TOTAL_TAKES":"4","UNIQUE_ZONES":"1","DISTANCE":"  0","DURATION":"0.0"},{"CHANGE":"<nobr class=\"up\">+2<\/nobr>","PLACE":171,"OLD":173,"NAME":"Crille_f","ALTSCORE":"358","DIFF":"35%","TOTAL_SCORE":"1010","FLAG":"se","REGION_NAME":"J\u00f6nk\u00f6ping","TOTAL_TAKES":"4","UNIQUE_ZONES":"1","DISTANCE":"  0","DURATION":"0.4"},{"CHANGE":"<nobr class=\"up\">+6<\/nobr>","PLACE":172,"OLD":178,"NAME":"ALarsson","ALTSCORE":"358","DIFF":"38%","TOTAL_SCORE":"941","FLAG":"se","REGION_NAME":"J\u00f6nk\u00f6ping","TOTAL_TAKES":"4","UNIQUE_ZONES":"1","DISTANCE":"  0","DURATION":"0.0"},{"CHANGE":"<nobr class=\"up\">+12<\/nobr>","PLACE":173,"OLD":185,"NAME":"Hall\u00e5ojd\u00e5","ALTSCORE":"358","DIFF":"46%","TOTAL_SCORE":"771","FLAG":"se","REGION_NAME":"J\u00f6nk\u00f6ping","TOTAL_TAKES":"4","UNIQUE_ZONES":"1","DISTANCE":"  0","DURATION":"0.4"},{"CHANGE":"<nobr class=\"up\">+12<\/nobr>","PLACE":174,"OLD":186,"NAME":"LoveN0rdh79","ALTSCORE":"300","DIFF":"39%","TOTAL_SCORE":"757","FLAG":"se","REGION_NAME":"J\u00f6nk\u00f6ping","TOTAL_TAKES":"3","UNIQUE_ZONES":"1","DISTANCE":"  0","DURATION":"0.0"},{"CHANGE":"<nobr class=\"down\">-37<\/nobr>","PLACE":175,"OLD":138,"NAME":"peter70sko","ALTSCORE":"300","DIFF":"18%","TOTAL_SCORE":"1622","FLAG":"se","REGION_NAME":"J\u00f6nk\u00f6ping","TOTAL_TAKES":"3","UNIQUE_ZONES":"1","DISTANCE":"  0","DURATION":"0.2"},{"CHANGE":"<nobr class=\"up\">+20<\/nobr>","PLACE":176,"OLD":196,"NAME":"bajsahit","ALTSCORE":"300","DIFF":"49%","TOTAL_SCORE":"605","FLAG":"se","REGION_NAME":"J\u00f6nk\u00f6ping","TOTAL_TAKES":"3","UNIQUE_ZONES":"1","DISTANCE":"  0","DURATION":"0.0"},{"CHANGE":"<nobr class=\"up\">+16<\/nobr>","PLACE":177,"OLD":193,"NAME":"Ralfe","ALTSCORE":"300","DIFF":"46%","TOTAL_SCORE":"645","FLAG":"se","REGION_NAME":"J\u00f6nk\u00f6ping","TOTAL_TAKES":"3","UNIQUE_ZONES":"1","DISTANCE":"  0","DURATION":"0.0"},{"CHANGE":"<nobr class=\"up\">+16<\/nobr>","PLACE":178,"OLD":194,"NAME":"nelliejeldez","ALTSCORE":"300","DIFF":"46%","TOTAL_SCORE":"641","FLAG":"se","REGION_NAME":"J\u00f6nk\u00f6ping","TOTAL_TAKES":"3","UNIQUE_ZONES":"1","DISTANCE":"  0","DURATION":"0.0"},{"CHANGE":"<nobr class=\"down\">-4<\/nobr>","PLACE":179,"OLD":175,"NAME":"Janbananberg","ALTSCORE":"300","DIFF":"30%","TOTAL_SCORE":"981","FLAG":"se","REGION_NAME":"J\u00f6nk\u00f6ping","TOTAL_TAKES":"3","UNIQUE_ZONES":"1","DISTANCE":"  0","DURATION":"0.6"},{"CHANGE":"<nobr class=\"up\">+3<\/nobr>","PLACE":180,"OLD":183,"NAME":"Rainboweyes","ALTSCORE":"300","DIFF":"35%","TOTAL_SCORE":"845","FLAG":"se","REGION_NAME":"J\u00f6nk\u00f6ping","TOTAL_TAKES":"3","UNIQUE_ZONES":"1","DISTANCE":"  0","DURATION":"0.0"},{"CHANGE":"<nobr class=\"up\">+7<\/nobr>","PLACE":181,"OLD":188,"NAME":"Stigsson3","ALTSCORE":"300","DIFF":"42%","TOTAL_SCORE":"702","FLAG":"se","REGION_NAME":"J\u00f6nk\u00f6ping","TOTAL_TAKES":"3","UNIQUE_ZONES":"1","DISTANCE":"  0","DURATION":"0.0"},{"CHANGE":"<nobr class=\"up\">+15<\/nobr>","PLACE":182,"OLD":197,"NAME":"A,C,F,R","ALTSCORE":"300","DIFF":"51%","TOTAL_SCORE":"586","FLAG":"se","REGION_NAME":"J\u00f6nk\u00f6ping","TOTAL_TAKES":"3","UNIQUE_ZONES":"1","DISTANCE":"  0","DURATION":"0.0"},{"CHANGE":"<nobr class=\"up\">+7<\/nobr>","PLACE":183,"OLD":190,"NAME":"EmazeY","ALTSCORE":"300","DIFF":"43%","TOTAL_SCORE":"694","FLAG":"se","REGION_NAME":"J\u00f6nk\u00f6ping","TOTAL_TAKES":"3","UNIQUE_ZONES":"1","DISTANCE":"  0","DURATION":"0.0"},{"CHANGE":"<nobr class=\"down\">-25<\/nobr>","PLACE":184,"OLD":159,"NAME":"sweest","ALTSCORE":"300","DIFF":"23%","TOTAL_SCORE":"1257","FLAG":"se","REGION_NAME":"J\u00f6nk\u00f6ping","TOTAL_TAKES":"3","UNIQUE_ZONES":"1","DISTANCE":"  0","DURATION":"0.0"},{"CHANGE":"<nobr class=\"up\">+4<\/nobr>","PLACE":185,"OLD":189,"NAME":"lolo,ema,towa","ALTSCORE":"300","DIFF":"42%","TOTAL_SCORE":"699","FLAG":"se","REGION_NAME":"J\u00f6nk\u00f6ping","TOTAL_TAKES":"3","UNIQUE_ZONES":"1","DISTANCE":"  0","DURATION":"0.0"},{"CHANGE":"<nobr class=\"up\">+6<\/nobr>","PLACE":186,"OLD":192,"NAME":"tildeyas","ALTSCORE":"300","DIFF":"45%","TOTAL_SCORE":"666","FLAG":"se","REGION_NAME":"J\u00f6nk\u00f6ping","TOTAL_TAKES":"3","UNIQUE_ZONES":"1","DISTANCE":"  0","DURATION":"0.0"},{"CHANGE":"<nobr class=\"down\">-44<\/nobr>","PLACE":187,"OLD":143,"NAME":"ALMAPALMA.SE","ALTSCORE":"300","DIFF":"19%","TOTAL_SCORE":"1537","FLAG":"se","REGION_NAME":"J\u00f6nk\u00f6ping","TOTAL_TAKES":"3","UNIQUE_ZONES":"1","DISTANCE":"  0","DURATION":"0.5"},{"CHANGE":"<nobr class=\"down\">-14<\/nobr>","PLACE":188,"OLD":174,"NAME":"Kullen2","ALTSCORE":"300","DIFF":"29%","TOTAL_SCORE":"1001","FLAG":"se","REGION_NAME":"J\u00f6nk\u00f6ping","TOTAL_TAKES":"3","UNIQUE_ZONES":"1","DISTANCE":"  0","DURATION":"0.0"},{"CHANGE":"<nobr class=\"up\">+18<\/nobr>","PLACE":189,"OLD":207,"NAME":"Ylpon","ALTSCORE":"243","DIFF":"51%","TOTAL_SCORE":"470","FLAG":"se","REGION_NAME":"J\u00f6nk\u00f6ping","TOTAL_TAKES":"2","UNIQUE_ZONES":"1","DISTANCE":"  0","DURATION":"0.0"},{"CHANGE":"<nobr class=\"up\">+5<\/nobr>","PLACE":190,"OLD":195,"NAME":"caryde","ALTSCORE":"243","DIFF":"38%","TOTAL_SCORE":"639","FLAG":"se","REGION_NAME":"J\u00f6nk\u00f6ping","TOTAL_TAKES":"2","UNIQUE_ZONES":"1","DISTANCE":"  0","DURATION":"0.3"},{"CHANGE":"<nobr class=\"up\">+26<\/nobr>","PLACE":191,"OLD":217,"NAME":"VilleEr\u00f6vraren","ALTSCORE":"243","DIFF":"72%","TOTAL_SCORE":"333","FLAG":"se","REGION_NAME":"J\u00f6nk\u00f6ping","TOTAL_TAKES":"2","UNIQUE_ZONES":"1","DISTANCE":"  0","DURATION":"0.0"},{"CHANGE":"<nobr class=\"up\">+12<\/nobr>","PLACE":192,"OLD":204,"NAME":"HkNd","ALTSCORE":"243","DIFF":"48%","TOTAL_SCORE":"497","FLAG":"se","REGION_NAME":"J\u00f6nk\u00f6ping","TOTAL_TAKES":"2","UNIQUE_ZONES":"1","DISTANCE":"  0","DURATION":"0.1"},{"CHANGE":"<nobr class=\"up\">+12<\/nobr>","PLACE":193,"OLD":205,"NAME":"elizakrasnqii","ALTSCORE":"243","DIFF":"49%","TOTAL_SCORE":"495","FLAG":"se","REGION_NAME":"J\u00f6nk\u00f6ping","TOTAL_TAKES":"2","UNIQUE_ZONES":"1","DISTANCE":"  0","DURATION":"0.2"},{"CHANGE":"<nobr class=\"up\">+14<\/nobr>","PLACE":194,"OLD":208,"NAME":"nej.","ALTSCORE":"243","DIFF":"53%","TOTAL_SCORE":"452","FLAG":"se","REGION_NAME":"J\u00f6nk\u00f6ping","TOTAL_TAKES":"2","UNIQUE_ZONES":"1","DISTANCE":"  0","DURATION":"0.0"},{"CHANGE":"<nobr class=\"up\">+15<\/nobr>","PLACE":195,"OLD":210,"NAME":"jolineeeeeee","ALTSCORE":"243","DIFF":"55%","TOTAL_SCORE":"437","FLAG":"se","REGION_NAME":"J\u00f6nk\u00f6ping","TOTAL_TAKES":"2","UNIQUE_ZONES":"1","DISTANCE":"  0","DURATION":"0.0"},{"CHANGE":"<nobr class=\"up\">+4<\/nobr>","PLACE":196,"OLD":200,"NAME":"Prosperia","ALTSCORE":"243","DIFF":"44%","TOTAL_SCORE":"552","FLAG":"se","REGION_NAME":"J\u00f6nk\u00f6ping","TOTAL_TAKES":"2","UNIQUE_ZONES":"1","DISTANCE":"  0","DURATION":"0.0"},{"CHANGE":"<nobr class=\"down\">-44<\/nobr>","PLACE":197,"OLD":153,"NAME":"TNT","ALTSCORE":"243","DIFF":"18%","TOTAL_SCORE":"1298","FLAG":"se","REGION_NAME":"J\u00f6nk\u00f6ping","TOTAL_TAKES":"2","UNIQUE_ZONES":"1","DISTANCE":"  0","DURATION":"0.0"},{"CHANGE":"<nobr class=\"down\">-16<\/nobr>","PLACE":198,"OLD":182,"NAME":"Everly","ALTSCORE":"243","DIFF":"27%","TOTAL_SCORE":"872","FLAG":"se","REGION_NAME":"J\u00f6nk\u00f6ping","TOTAL_TAKES":"2","UNIQUE_ZONES":"1","DISTANCE":"  0","DURATION":"0.0"},{"CHANGE":"<nobr class=\"up\">+7<\/nobr>","PLACE":199,"OLD":206,"NAME":"Eidur","ALTSCORE":"243","DIFF":"51%","TOTAL_SCORE":"475","FLAG":"se","REGION_NAME":"J\u00f6nk\u00f6ping","TOTAL_TAKES":"2","UNIQUE_ZONES":"1","DISTANCE":"  0","DURATION":"0.1"},{"CHANGE":"<nobr class=\"up\">+11<\/nobr>","PLACE":200,"OLD":211,"NAME":"Hannaaaaaaaaaa","ALTSCORE":"243","DIFF":"57%","TOTAL_SCORE":"423","FLAG":"se","REGION_NAME":"J\u00f6nk\u00f6ping","TOTAL_TAKES":"2","UNIQUE_ZONES":"1","DISTANCE":"  0","DURATION":"0.0"},{"CHANGE":"<nobr class=\"down\">-17<\/nobr>","PLACE":201,"OLD":184,"NAME":"DanielKarlsson","ALTSCORE":"243","DIFF":"30%","TOTAL_SCORE":"806","FLAG":"se","REGION_NAME":"J\u00f6nk\u00f6ping","TOTAL_TAKES":"2","UNIQUE_ZONES":"1","DISTANCE":"  0","DURATION":"0.0"},{"CHANGE":"<nobr class=\"up\">+1<\/nobr>","PLACE":202,"OLD":203,"NAME":"xplor","ALTSCORE":"243","DIFF":"47%","TOTAL_SCORE":"511","FLAG":"se","REGION_NAME":"J\u00f6nk\u00f6ping","TOTAL_TAKES":"2","UNIQUE_ZONES":"1","DISTANCE":"  0","DURATION":"0.8"},{"CHANGE":"<nobr class=\"down\">-5<\/nobr>","PLACE":203,"OLD":198,"NAME":"LeBron.James","ALTSCORE":"243","DIFF":"42%","TOTAL_SCORE":"578","FLAG":"se","REGION_NAME":"J\u00f6nk\u00f6ping","TOTAL_TAKES":"2","UNIQUE_ZONES":"1","DISTANCE":"  0","DURATION":"0.1"},{"CHANGE":"<nobr class=\"down\">-23<\/nobr>","PLACE":204,"OLD":181,"NAME":"Torben_SS","ALTSCORE":"243","DIFF":"26%","TOTAL_SCORE":"928","FLAG":"se","REGION_NAME":"J\u00f6nk\u00f6ping","TOTAL_TAKES":"2","UNIQUE_ZONES":"1","DISTANCE":"  0","DURATION":"0.0"},{"CHANGE":"<nobr class=\"down\">-6<\/nobr>","PLACE":205,"OLD":199,"NAME":"mimmam","ALTSCORE":"243","DIFF":"42%","TOTAL_SCORE":"566","FLAG":"se","REGION_NAME":"J\u00f6nk\u00f6ping","TOTAL_TAKES":"2","UNIQUE_ZONES":"1","DISTANCE":"  0","DURATION":"0.0"},{"CHANGE":"<nobr class=\"down\">-5<\/nobr>","PLACE":206,"OLD":201,"NAME":"Kicken","ALTSCORE":"243","DIFF":"44%","TOTAL_SCORE":"542","FLAG":"se","REGION_NAME":"J\u00f6nk\u00f6ping","TOTAL_TAKES":"2","UNIQUE_ZONES":"1","DISTANCE":"  0","DURATION":"0.0"},{"CHANGE":"<nobr class=\"down\">-36<\/nobr>","PLACE":207,"OLD":171,"NAME":"klea,Alice","ALTSCORE":"231","DIFF":"22%","TOTAL_SCORE":"1023","FLAG":"se","REGION_NAME":"J\u00f6nk\u00f6ping","TOTAL_TAKES":"5","UNIQUE_ZONES":"0","DISTANCE":"  0","DURATION":"0.5"},{"CHANGE":"<nobr class=\"down\">-28<\/nobr>","PLACE":208,"OLD":180,"NAME":"Taendved","ALTSCORE":"231","DIFF":"24%","TOTAL_SCORE":"929","FLAG":"se","REGION_NAME":"J\u00f6nk\u00f6ping","TOTAL_TAKES":"5","UNIQUE_ZONES":"0","DISTANCE":"  0","DURATION":"0.0"},{"CHANGE":"<nobr class=\"down\">-22<\/nobr>","PLACE":209,"OLD":187,"NAME":"Biltan","ALTSCORE":"185","DIFF":"25%","TOTAL_SCORE":"736","FLAG":"se","REGION_NAME":"J\u00f6nk\u00f6ping","TOTAL_TAKES":"1","UNIQUE_ZONES":"1","DISTANCE":"  0","DURATION":"0.0"},{"CHANGE":"<nobr class=\"up\">+5<\/nobr>","PLACE":210,"OLD":215,"NAME":"MalvaHenrysson","ALTSCORE":"185","DIFF":"52%","TOTAL_SCORE":"352","FLAG":"se","REGION_NAME":"J\u00f6nk\u00f6ping","TOTAL_TAKES":"1","UNIQUE_ZONES":"1","DISTANCE":"  0","DURATION":"0.1"},{"CHANGE":"<nobr class=\"up\">+5<\/nobr>","PLACE":211,"OLD":216,"NAME":"JFG","ALTSCORE":"185","DIFF":"54%","TOTAL_SCORE":"340","FLAG":"se","REGION_NAME":"J\u00f6nk\u00f6ping","TOTAL_TAKES":"1","UNIQUE_ZONES":"1","DISTANCE":"  0","DURATION":"0.0"},{"CHANGE":"-","PLACE":212,"OLD":212,"NAME":"Olympia7","ALTSCORE":"185","DIFF":"43%","TOTAL_SCORE":"421","FLAG":"se","REGION_NAME":"J\u00f6nk\u00f6ping","TOTAL_TAKES":"1","UNIQUE_ZONES":"1","DISTANCE":"  0","DURATION":"0.0"},{"CHANGE":"<nobr class=\"down\">-22<\/nobr>","PLACE":213,"OLD":191,"NAME":"AmoMuayid","ALTSCORE":"115","DIFF":"16%","TOTAL_SCORE":"679","FLAG":"se","REGION_NAME":"J\u00f6nk\u00f6ping","TOTAL_TAKES":"3","UNIQUE_ZONES":"0","DISTANCE":"  0","DURATION":"0.0"},{"CHANGE":"<nobr class=\"up\">+23<\/nobr>","PLACE":214,"OLD":237,"NAME":"Wallersj\u00f6","ALTSCORE":"0","DIFF":"0%","TOTAL_SCORE":"152","FLAG":"se","REGION_NAME":"J\u00f6nk\u00f6ping","TOTAL_TAKES":"0","UNIQUE_ZONES":null,"DISTANCE":"  0","DURATION":"0.0"},{"CHANGE":"<nobr class=\"up\">+14<\/nobr>","PLACE":215,"OLD":229,"NAME":"RS_","ALTSCORE":"0","DIFF":"0%","TOTAL_SCORE":"175","FLAG":"se","REGION_NAME":"J\u00f6nk\u00f6ping","TOTAL_TAKES":"0","UNIQUE_ZONES":null,"DISTANCE":"  0","DURATION":"0.0"},{"CHANGE":"<nobr class=\"up\">+3<\/nobr>","PLACE":216,"OLD":219,"NAME":"mahake","ALTSCORE":"0","DIFF":"0%","TOTAL_SCORE":"300","FLAG":"se","REGION_NAME":"J\u00f6nk\u00f6ping","TOTAL_TAKES":"0","UNIQUE_ZONES":null,"DISTANCE":"  0","DURATION":"0.0"},{"CHANGE":"<nobr class=\"down\">-8<\/nobr>","PLACE":217,"OLD":209,"NAME":"Mia1971","ALTSCORE":"0","DIFF":"0%","TOTAL_SCORE":"446","FLAG":"se","REGION_NAME":"J\u00f6nk\u00f6ping","TOTAL_TAKES":"0","UNIQUE_ZONES":null,"DISTANCE":"  0","DURATION":"0.0"},{"CHANGE":"<nobr class=\"up\">+7<\/nobr>","PLACE":218,"OLD":225,"NAME":"Helga1966","ALTSCORE":"0","DIFF":"0%","TOTAL_SCORE":"222","FLAG":"se","REGION_NAME":"J\u00f6nk\u00f6ping","TOTAL_TAKES":"0","UNIQUE_ZONES":null,"DISTANCE":"  0","DURATION":"0.0"},{"CHANGE":"<nobr class=\"up\">+12<\/nobr>","PLACE":219,"OLD":231,"NAME":"Cookie","ALTSCORE":"0","DIFF":"0%","TOTAL_SCORE":"171","FLAG":"se","REGION_NAME":"J\u00f6nk\u00f6ping","TOTAL_TAKES":"0","UNIQUE_ZONES":null,"DISTANCE":"  0","DURATION":"0.0"},{"CHANGE":"<nobr class=\"up\">+13<\/nobr>","PLACE":220,"OLD":233,"NAME":"HBJ","ALTSCORE":"0","DIFF":"0%","TOTAL_SCORE":"167","FLAG":"se","REGION_NAME":"J\u00f6nk\u00f6ping","TOTAL_TAKES":"0","UNIQUE_ZONES":null,"DISTANCE":"  0","DURATION":"0.0"},{"CHANGE":"<nobr class=\"up\">+9<\/nobr>","PLACE":221,"OLD":230,"NAME":"tuvarei1","ALTSCORE":"0","DIFF":"0%","TOTAL_SCORE":"172","FLAG":"se","REGION_NAME":"J\u00f6nk\u00f6ping","TOTAL_TAKES":"0","UNIQUE_ZONES":null,"DISTANCE":"  0","DURATION":"0.0"},{"CHANGE":"<nobr class=\"down\">-4<\/nobr>","PLACE":222,"OLD":218,"NAME":"ASTV\u00c5","ALTSCORE":"0","DIFF":"0%","TOTAL_SCORE":"323","FLAG":"se","REGION_NAME":"J\u00f6nk\u00f6ping","TOTAL_TAKES":"0","UNIQUE_ZONES":null,"DISTANCE":"  0","DURATION":"0.0"},{"CHANGE":"<nobr class=\"down\">-10<\/nobr>","PLACE":223,"OLD":213,"NAME":"DrR\u00f6j","ALTSCORE":"0","DIFF":"0%","TOTAL_SCORE":"384","FLAG":"se","REGION_NAME":"J\u00f6nk\u00f6ping","TOTAL_TAKES":"1","UNIQUE_ZONES":"0","DISTANCE":"  0","DURATION":"0.1"},{"CHANGE":"<nobr class=\"down\">-10<\/nobr>","PLACE":224,"OLD":214,"NAME":"Lingonmannen","ALTSCORE":"0","DIFF":"0%","TOTAL_SCORE":"365","FLAG":"se","REGION_NAME":"J\u00f6nk\u00f6ping","TOTAL_TAKES":"0","UNIQUE_ZONES":null,"DISTANCE":"  0","DURATION":"0.0"},{"CHANGE":"<nobr class=\"down\">-3<\/nobr>","PLACE":225,"OLD":222,"NAME":"Leetharus","ALTSCORE":"0","DIFF":"0%","TOTAL_SCORE":"240","FLAG":"se","REGION_NAME":"J\u00f6nk\u00f6ping","TOTAL_TAKES":"0","UNIQUE_ZONES":null,"DISTANCE":"  0","DURATION":"0.0"},{"CHANGE":"<nobr class=\"up\">+6<\/nobr>","PLACE":226,"OLD":232,"NAME":"emma.berg234","ALTSCORE":"0","DIFF":"0%","TOTAL_SCORE":"170","FLAG":"se","REGION_NAME":"J\u00f6nk\u00f6ping","TOTAL_TAKES":"0","UNIQUE_ZONES":null,"DISTANCE":"  0","DURATION":"0.0"},{"CHANGE":"<nobr class=\"down\">-6<\/nobr>","PLACE":227,"OLD":221,"NAME":"enje","ALTSCORE":"0","DIFF":"0%","TOTAL_SCORE":"250","FLAG":"se","REGION_NAME":"J\u00f6nk\u00f6ping","TOTAL_TAKES":"0","UNIQUE_ZONES":null,"DISTANCE":"  0","DURATION":"0.0"},{"CHANGE":"<nobr class=\"down\">-26<\/nobr>","PLACE":228,"OLD":202,"NAME":"MCrommert","ALTSCORE":"0","DIFF":"0%","TOTAL_SCORE":"528","FLAG":"se","REGION_NAME":"J\u00f6nk\u00f6ping","TOTAL_TAKES":"0","UNIQUE_ZONES":null,"DISTANCE":"  0","DURATION":"0.0"},{"CHANGE":"<nobr class=\"up\">+5<\/nobr>","PLACE":229,"OLD":234,"NAME":"Milhug","ALTSCORE":"0","DIFF":"0%","TOTAL_SCORE":"164","FLAG":"se","REGION_NAME":"J\u00f6nk\u00f6ping","TOTAL_TAKES":"0","UNIQUE_ZONES":null,"DISTANCE":"  0","DURATION":"0.0"},{"CHANGE":"<nobr class=\"down\">-7<\/nobr>","PLACE":230,"OLD":223,"NAME":"MeyAlvJol","ALTSCORE":"0","DIFF":"0%","TOTAL_SCORE":"233","FLAG":"se","REGION_NAME":"J\u00f6nk\u00f6ping","TOTAL_TAKES":"0","UNIQUE_ZONES":null,"DISTANCE":"  0","DURATION":"0.0"},{"CHANGE":"<nobr class=\"up\">+5<\/nobr>","PLACE":231,"OLD":236,"NAME":"Turflickan","ALTSCORE":"0","DIFF":"0%","TOTAL_SCORE":"158","FLAG":"se","REGION_NAME":"J\u00f6nk\u00f6ping","TOTAL_TAKES":"0","UNIQUE_ZONES":null,"DISTANCE":"  0","DURATION":"0.0"},{"CHANGE":"<nobr class=\"down\">-4<\/nobr>","PLACE":232,"OLD":228,"NAME":"Bibliotekarien","ALTSCORE":"0","DIFF":"0%","TOTAL_SCORE":"179","FLAG":"se","REGION_NAME":"J\u00f6nk\u00f6ping","TOTAL_TAKES":"0","UNIQUE_ZONES":null,"DISTANCE":"  0","DURATION":"0.0"},{"CHANGE":"<nobr class=\"down\">-6<\/nobr>","PLACE":233,"OLD":227,"NAME":"NinaC","ALTSCORE":"0","DIFF":"0%","TOTAL_SCORE":"201","FLAG":"se","REGION_NAME":"J\u00f6nk\u00f6ping","TOTAL_TAKES":"0","UNIQUE_ZONES":null,"DISTANCE":"  0","DURATION":"0.0"},{"CHANGE":"<nobr class=\"up\">+4<\/nobr>","PLACE":234,"OLD":238,"NAME":"Daliya","ALTSCORE":"0","DIFF":"0%","TOTAL_SCORE":"141","FLAG":"se","REGION_NAME":"J\u00f6nk\u00f6ping","TOTAL_TAKES":"0","UNIQUE_ZONES":null,"DISTANCE":"  0","DURATION":"0.0"},{"CHANGE":"<nobr class=\"down\">-11<\/nobr>","PLACE":235,"OLD":224,"NAME":"helebis","ALTSCORE":"0","DIFF":"0%","TOTAL_SCORE":"226","FLAG":"se","REGION_NAME":"J\u00f6nk\u00f6ping","TOTAL_TAKES":"0","UNIQUE_ZONES":null,"DISTANCE":"  0","DURATION":"0.0"},{"CHANGE":"<nobr class=\"down\">-16<\/nobr>","PLACE":236,"OLD":220,"NAME":"Turfsemlan","ALTSCORE":"0","DIFF":"0%","TOTAL_SCORE":"286","FLAG":"se","REGION_NAME":"J\u00f6nk\u00f6ping","TOTAL_TAKES":"0","UNIQUE_ZONES":null,"DISTANCE":"  0","DURATION":"0.0"},{"CHANGE":"<nobr class=\"down\">-11<\/nobr>","PLACE":237,"OLD":226,"NAME":"ThePhiddler","ALTSCORE":"0","DIFF":"0%","TOTAL_SCORE":"212","FLAG":"se","REGION_NAME":"J\u00f6nk\u00f6ping","TOTAL_TAKES":"0","UNIQUE_ZONES":null,"DISTANCE":"  0","DURATION":"0.0"},{"CHANGE":"<nobr class=\"down\">-3<\/nobr>","PLACE":238,"OLD":235,"NAME":"Negerkungen","ALTSCORE":"0","DIFF":"0%","TOTAL_SCORE":"159","FLAG":"se","REGION_NAME":"J\u00f6nk\u00f6ping","TOTAL_TAKES":"0","UNIQUE_ZONES":null,"DISTANCE":"  0","DURATION":"0.0"}]