[{"CHANGE":"<nobr class=\"up\">+1<\/nobr>","PLACE":1,"OLD":2,"NAME":"<a href=\"https:\/\/frut.zundin.se\/user_round.php?userid=Sven_R&roundid=179\" target=\"_blank\" rel=\"noopener noreferrer\">Sven_R<\/a>","ALTSCORE":"105248","DIFF":"44%","TOTAL_SCORE":"238093","COUNTRY":"<a href=\"https:\/\/turfmedals.com\/profile\/Sven_R\" target=\"_blank\" rel=\"noopener noreferrer\"><img src=\"https:\/\/flagcdn.com\/h20\/de.png\" height=\"20\" alt=\"de\"><\/a>","REGION_NAME":"Brandenburg","TOTAL_TAKES":"917","UNIQUE_ZONES":"547","DISTANCE":"517","DURATION":"36.4"},{"CHANGE":"<nobr class=\"down\">-1<\/nobr>","PLACE":2,"OLD":1,"NAME":"<a href=\"https:\/\/frut.zundin.se\/user_round.php?userid=DasHuhn&roundid=179\" target=\"_blank\" rel=\"noopener noreferrer\">DasHuhn<\/a>","ALTSCORE":"81588","DIFF":"33%","TOTAL_SCORE":"240776","COUNTRY":"<a href=\"https:\/\/turfmedals.com\/profile\/DasHuhn\" target=\"_blank\" rel=\"noopener noreferrer\"><img src=\"https:\/\/flagcdn.com\/h20\/de.png\" height=\"20\" alt=\"de\"><\/a>","REGION_NAME":"Brandenburg","TOTAL_TAKES":"720","UNIQUE_ZONES":"423","DISTANCE":"243","DURATION":"18.6"},{"CHANGE":"-","PLACE":3,"OLD":3,"NAME":"<a href=\"https:\/\/frut.zundin.se\/user_round.php?userid=muddi&roundid=179\" target=\"_blank\" rel=\"noopener noreferrer\">muddi<\/a>","ALTSCORE":"2617","DIFF":"50%","TOTAL_SCORE":"5159","COUNTRY":"<a href=\"https:\/\/turfmedals.com\/profile\/muddi\" target=\"_blank\" rel=\"noopener noreferrer\"><img src=\"https:\/\/flagcdn.com\/h20\/de.png\" height=\"20\" alt=\"de\"><\/a>","REGION_NAME":"Brandenburg","TOTAL_TAKES":"25","UNIQUE_ZONES":"19","DISTANCE":"  6","DURATION":"0.5"},{"CHANGE":"-","PLACE":4,"OLD":4,"NAME":"<a href=\"https:\/\/frut.zundin.se\/user_round.php?userid=%28123%29&roundid=179\" target=\"_blank\" rel=\"noopener noreferrer\">(123)<\/a>","ALTSCORE":"1817","DIFF":"41%","TOTAL_SCORE":"4422","COUNTRY":"<a href=\"https:\/\/turfmedals.com\/profile\/%28123%29\" target=\"_blank\" rel=\"noopener noreferrer\"><img src=\"https:\/\/flagcdn.com\/h20\/de.png\" height=\"20\" alt=\"de\"><\/a>","REGION_NAME":"Brandenburg","TOTAL_TAKES":"17","UNIQUE_ZONES":"15","DISTANCE":"  0","DURATION":"0.0"},{"CHANGE":"-","PLACE":5,"OLD":5,"NAME":"<a href=\"https:\/\/frut.zundin.se\/user_round.php?userid=eichwalde&roundid=179\" target=\"_blank\" rel=\"noopener noreferrer\">eichwalde<\/a>","ALTSCORE":"903","DIFF":"60%","TOTAL_SCORE":"1497","COUNTRY":"<a href=\"https:\/\/turfmedals.com\/profile\/eichwalde\" target=\"_blank\" rel=\"noopener noreferrer\"><img src=\"https:\/\/flagcdn.com\/h20\/de.png\" height=\"20\" alt=\"de\"><\/a>","REGION_NAME":"Brandenburg","TOTAL_TAKES":"8","UNIQUE_ZONES":"6","DISTANCE":"  0","DURATION":"0.0"},{"CHANGE":"-","PLACE":6,"OLD":6,"NAME":"<a href=\"https:\/\/frut.zundin.se\/user_round.php?userid=Svens.&roundid=179\" target=\"_blank\" rel=\"noopener noreferrer\">Svens.<\/a>","ALTSCORE":"901","DIFF":"60%","TOTAL_SCORE":"1497","COUNTRY":"<a href=\"https:\/\/turfmedals.com\/profile\/Svens.\" target=\"_blank\" rel=\"noopener noreferrer\"><img src=\"https:\/\/flagcdn.com\/h20\/de.png\" height=\"20\" alt=\"de\"><\/a>","REGION_NAME":"Brandenburg","TOTAL_TAKES":"8","UNIQUE_ZONES":"4","DISTANCE":"  0","DURATION":"0.0"},{"CHANGE":"-","PLACE":7,"OLD":7,"NAME":"<a href=\"https:\/\/frut.zundin.se\/user_round.php?userid=Goldfische&roundid=179\" target=\"_blank\" rel=\"noopener noreferrer\">Goldfische<\/a>","ALTSCORE":"800","DIFF":"59%","TOTAL_SCORE":"1340","COUNTRY":"<a href=\"https:\/\/turfmedals.com\/profile\/Goldfische\" target=\"_blank\" rel=\"noopener noreferrer\"><img src=\"https:\/\/flagcdn.com\/h20\/de.png\" height=\"20\" alt=\"de\"><\/a>","REGION_NAME":"Brandenburg","TOTAL_TAKES":"7","UNIQUE_ZONES":"5","DISTANCE":"  0","DURATION":"0.2"},{"CHANGE":"-","PLACE":8,"OLD":8,"NAME":"<a href=\"https:\/\/frut.zundin.se\/user_round.php?userid=Ysop&roundid=179\" target=\"_blank\" rel=\"noopener noreferrer\">Ysop<\/a>","ALTSCORE":"200","DIFF":"37%","TOTAL_SCORE":"540","COUNTRY":"<a href=\"https:\/\/turfmedals.com\/profile\/Ysop\" target=\"_blank\" rel=\"noopener noreferrer\"><img src=\"https:\/\/flagcdn.com\/h20\/de.png\" height=\"20\" alt=\"de\"><\/a>","REGION_NAME":"Brandenburg","TOTAL_TAKES":"1","UNIQUE_ZONES":"1","DISTANCE":"  0","DURATION":"0.0"}]