{"categories":[{"name":"World","link":"https:\/\/turfutils.github.io\/cache\/altscore_b\/2025-05.html"},{"name":"nl","subcategories":[{"name":"ALL","link":"https:\/\/turfutils.github.io\/cache\/altscore_b\/2025-05\/2025-05_nl.html"},{"name":"Utrecht","link":"https:\/\/turfutils.github.io\/cache\/altscore_b\/2025-05\/2025-05_95.html"},{"name":"Limburg","link":"https:\/\/turfutils.github.io\/cache\/altscore_b\/2025-05\/2025-05_106.html"},{"name":"Friesland","link":"https:\/\/turfutils.github.io\/cache\/altscore_b\/2025-05\/2025-05_107.html"},{"name":"Groningen","link":"https:\/\/turfutils.github.io\/cache\/altscore_b\/2025-05\/2025-05_108.html"},{"name":"Drenthe","link":"https:\/\/turfutils.github.io\/cache\/altscore_b\/2025-05\/2025-05_109.html"},{"name":"Flevoland","link":"https:\/\/turfutils.github.io\/cache\/altscore_b\/2025-05\/2025-05_110.html"},{"name":"Gelderland","link":"https:\/\/turfutils.github.io\/cache\/altscore_b\/2025-05\/2025-05_111.html"},{"name":"Noord-Brabant","link":"https:\/\/turfutils.github.io\/cache\/altscore_b\/2025-05\/2025-05_112.html"},{"name":"Zeeland","link":"https:\/\/turfutils.github.io\/cache\/altscore_b\/2025-05\/2025-05_113.html"},{"name":"Overijssel","link":"https:\/\/turfutils.github.io\/cache\/altscore_b\/2025-05\/2025-05_115.html"},{"name":"Noord-Holland","link":"https:\/\/turfutils.github.io\/cache\/altscore_b\/2025-05\/2025-05_117.html"},{"name":"Zuid-Holland","link":"https:\/\/turfutils.github.io\/cache\/altscore_b\/2025-05\/2025-05_118.html"}]},{"name":"se","subcategories":[{"name":"ALL","link":"https:\/\/turfutils.github.io\/cache\/altscore_b\/2025-05\/2025-05_se.html"},{"name":"Norrbotten","link":"https:\/\/turfutils.github.io\/cache\/altscore_b\/2025-05\/2025-05_126.html"},{"name":"V\u00e4sterbotten","link":"https:\/\/turfutils.github.io\/cache\/altscore_b\/2025-05\/2025-05_127.html"},{"name":"J\u00e4mtland","link":"https:\/\/turfutils.github.io\/cache\/altscore_b\/2025-05\/2025-05_128.html"},{"name":"Dalarna","link":"https:\/\/turfutils.github.io\/cache\/altscore_b\/2025-05\/2025-05_129.html"},{"name":"V\u00e4rmland","link":"https:\/\/turfutils.github.io\/cache\/altscore_b\/2025-05\/2025-05_130.html"},{"name":"\u00d6rebro","link":"https:\/\/turfutils.github.io\/cache\/altscore_b\/2025-05\/2025-05_131.html"},{"name":"V\u00e4stra G\u00f6taland","link":"https:\/\/turfutils.github.io\/cache\/altscore_b\/2025-05\/2025-05_132.html"},{"name":"J\u00f6nk\u00f6ping","link":"https:\/\/turfutils.github.io\/cache\/altscore_b\/2025-05\/2025-05_133.html"},{"name":"Halland","link":"https:\/\/turfutils.github.io\/cache\/altscore_b\/2025-05\/2025-05_134.html"},{"name":"Sk\u00e5ne","link":"https:\/\/turfutils.github.io\/cache\/altscore_b\/2025-05\/2025-05_135.html"},{"name":"Blekinge","link":"https:\/\/turfutils.github.io\/cache\/altscore_b\/2025-05\/2025-05_136.html"},{"name":"Kalmar","link":"https:\/\/turfutils.github.io\/cache\/altscore_b\/2025-05\/2025-05_137.html"},{"name":"Gotland","link":"https:\/\/turfutils.github.io\/cache\/altscore_b\/2025-05\/2025-05_138.html"},{"name":"\u00d6sterg\u00f6tland","link":"https:\/\/turfutils.github.io\/cache\/altscore_b\/2025-05\/2025-05_139.html"},{"name":"S\u00f6dermanland","link":"https:\/\/turfutils.github.io\/cache\/altscore_b\/2025-05\/2025-05_140.html"},{"name":"Stockholm","link":"https:\/\/turfutils.github.io\/cache\/altscore_b\/2025-05\/2025-05_141.html"},{"name":"Uppsala","link":"https:\/\/turfutils.github.io\/cache\/altscore_b\/2025-05\/2025-05_142.html"},{"name":"V\u00e4stmanland","link":"https:\/\/turfutils.github.io\/cache\/altscore_b\/2025-05\/2025-05_143.html"},{"name":"G\u00e4vleborg","link":"https:\/\/turfutils.github.io\/cache\/altscore_b\/2025-05\/2025-05_144.html"},{"name":"V\u00e4sternorrland","link":"https:\/\/turfutils.github.io\/cache\/altscore_b\/2025-05\/2025-05_145.html"},{"name":"Kronoberg","link":"https:\/\/turfutils.github.io\/cache\/altscore_b\/2025-05\/2025-05_147.html"}]},{"name":"Rest","subcategories":[{"name":"ALL","link":"https:\/\/turfutils.github.io\/cache\/altscore_b\/2025-05\/2025-05_Rest.html"},{"name":"Canada","link":"https:\/\/turfutils.github.io\/cache\/altscore_b\/2025-05\/2025-05_149.html"},{"name":"China","link":"https:\/\/turfutils.github.io\/cache\/altscore_b\/2025-05\/2025-05_150.html"},{"name":"England","link":"https:\/\/turfutils.github.io\/cache\/altscore_b\/2025-05\/2025-05_152.html"},{"name":"Germany","link":"https:\/\/turfutils.github.io\/cache\/altscore_b\/2025-05\/2025-05_153.html"},{"name":"France","link":"https:\/\/turfutils.github.io\/cache\/altscore_b\/2025-05\/2025-05_154.html"},{"name":"Italy","link":"https:\/\/turfutils.github.io\/cache\/altscore_b\/2025-05\/2025-05_155.html"},{"name":"Iceland","link":"https:\/\/turfutils.github.io\/cache\/altscore_b\/2025-05\/2025-05_178.html"},{"name":"Spain","link":"https:\/\/turfutils.github.io\/cache\/altscore_b\/2025-05\/2025-05_211.html"},{"name":"Austria","link":"https:\/\/turfutils.github.io\/cache\/altscore_b\/2025-05\/2025-05_212.html"},{"name":"Switzerland","link":"https:\/\/turfutils.github.io\/cache\/altscore_b\/2025-05\/2025-05_213.html"},{"name":"Belgium","link":"https:\/\/turfutils.github.io\/cache\/altscore_b\/2025-05\/2025-05_214.html"},{"name":"Greece","link":"https:\/\/turfutils.github.io\/cache\/altscore_b\/2025-05\/2025-05_215.html"},{"name":"Czech Republic","link":"https:\/\/turfutils.github.io\/cache\/altscore_b\/2025-05\/2025-05_216.html"},{"name":"Latvia","link":"https:\/\/turfutils.github.io\/cache\/altscore_b\/2025-05\/2025-05_217.html"},{"name":"Estonia","link":"https:\/\/turfutils.github.io\/cache\/altscore_b\/2025-05\/2025-05_218.html"},{"name":"Poland","link":"https:\/\/turfutils.github.io\/cache\/altscore_b\/2025-05\/2025-05_219.html"},{"name":"Thailand","link":"https:\/\/turfutils.github.io\/cache\/altscore_b\/2025-05\/2025-05_220.html"},{"name":"Japan","link":"https:\/\/turfutils.github.io\/cache\/altscore_b\/2025-05\/2025-05_221.html"},{"name":"Australia","link":"https:\/\/turfutils.github.io\/cache\/altscore_b\/2025-05\/2025-05_222.html"},{"name":"Turkey","link":"https:\/\/turfutils.github.io\/cache\/altscore_b\/2025-05\/2025-05_223.html"},{"name":"Bulgaria","link":"https:\/\/turfutils.github.io\/cache\/altscore_b\/2025-05\/2025-05_224.html"},{"name":"Croatia","link":"https:\/\/turfutils.github.io\/cache\/altscore_b\/2025-05\/2025-05_225.html"},{"name":"Cyprus","link":"https:\/\/turfutils.github.io\/cache\/altscore_b\/2025-05\/2025-05_228.html"},{"name":"Cabo Verde","link":"https:\/\/turfutils.github.io\/cache\/altscore_b\/2025-05\/2025-05_229.html"},{"name":"Malta","link":"https:\/\/turfutils.github.io\/cache\/altscore_b\/2025-05\/2025-05_230.html"},{"name":"Portugal","link":"https:\/\/turfutils.github.io\/cache\/altscore_b\/2025-05\/2025-05_231.html"},{"name":"Lithuania","link":"https:\/\/turfutils.github.io\/cache\/altscore_b\/2025-05\/2025-05_232.html"},{"name":"Brazil","link":"https:\/\/turfutils.github.io\/cache\/altscore_b\/2025-05\/2025-05_234.html"},{"name":"Slovakia","link":"https:\/\/turfutils.github.io\/cache\/altscore_b\/2025-05\/2025-05_235.html"},{"name":"Hungary","link":"https:\/\/turfutils.github.io\/cache\/altscore_b\/2025-05\/2025-05_236.html"},{"name":"Luxembourg","link":"https:\/\/turfutils.github.io\/cache\/altscore_b\/2025-05\/2025-05_237.html"},{"name":"Singapore","link":"https:\/\/turfutils.github.io\/cache\/altscore_b\/2025-05\/2025-05_239.html"},{"name":"Guatemala","link":"https:\/\/turfutils.github.io\/cache\/altscore_b\/2025-05\/2025-05_242.html"},{"name":"M\u00e9xico","link":"https:\/\/turfutils.github.io\/cache\/altscore_b\/2025-05\/2025-05_243.html"},{"name":"Honduras","link":"https:\/\/turfutils.github.io\/cache\/altscore_b\/2025-05\/2025-05_244.html"},{"name":"Belize","link":"https:\/\/turfutils.github.io\/cache\/altscore_b\/2025-05\/2025-05_245.html"},{"name":"El Salvador","link":"https:\/\/turfutils.github.io\/cache\/altscore_b\/2025-05\/2025-05_246.html"},{"name":"Nicaragua","link":"https:\/\/turfutils.github.io\/cache\/altscore_b\/2025-05\/2025-05_247.html"},{"name":"Costa Rica","link":"https:\/\/turfutils.github.io\/cache\/altscore_b\/2025-05\/2025-05_248.html"},{"name":"Panam\u00e1","link":"https:\/\/turfutils.github.io\/cache\/altscore_b\/2025-05\/2025-05_249.html"},{"name":"New Zealand","link":"https:\/\/turfutils.github.io\/cache\/altscore_b\/2025-05\/2025-05_250.html"},{"name":"Argentina","link":"https:\/\/turfutils.github.io\/cache\/altscore_b\/2025-05\/2025-05_251.html"},{"name":"Argentina","link":"https:\/\/turfutils.github.io\/cache\/altscore_b\/2025-05\/2025-05_252.html"},{"name":"Uruguay","link":"https:\/\/turfutils.github.io\/cache\/altscore_b\/2025-05\/2025-05_253.html"},{"name":"Paraguay","link":"https:\/\/turfutils.github.io\/cache\/altscore_b\/2025-05\/2025-05_254.html"},{"name":"Bolivia","link":"https:\/\/turfutils.github.io\/cache\/altscore_b\/2025-05\/2025-05_255.html"},{"name":"Chile","link":"https:\/\/turfutils.github.io\/cache\/altscore_b\/2025-05\/2025-05_256.html"},{"name":"Peru","link":"https:\/\/turfutils.github.io\/cache\/altscore_b\/2025-05\/2025-05_257.html"},{"name":"Ecuador","link":"https:\/\/turfutils.github.io\/cache\/altscore_b\/2025-05\/2025-05_258.html"},{"name":"Colombia","link":"https:\/\/turfutils.github.io\/cache\/altscore_b\/2025-05\/2025-05_259.html"},{"name":"Venezuela","link":"https:\/\/turfutils.github.io\/cache\/altscore_b\/2025-05\/2025-05_260.html"},{"name":"Puerto Rico","link":"https:\/\/turfutils.github.io\/cache\/altscore_b\/2025-05\/2025-05_261.html"},{"name":"Jamaica","link":"https:\/\/turfutils.github.io\/cache\/altscore_b\/2025-05\/2025-05_262.html"},{"name":"Cuba","link":"https:\/\/turfutils.github.io\/cache\/altscore_b\/2025-05\/2025-05_263.html"},{"name":"Bahamas","link":"https:\/\/turfutils.github.io\/cache\/altscore_b\/2025-05\/2025-05_264.html"},{"name":"Dominican Republic","link":"https:\/\/turfutils.github.io\/cache\/altscore_b\/2025-05\/2025-05_265.html"},{"name":"Ireland","link":"https:\/\/turfutils.github.io\/cache\/altscore_b\/2025-05\/2025-05_266.html"},{"name":"Egypt","link":"https:\/\/turfutils.github.io\/cache\/altscore_b\/2025-05\/2025-05_267.html"},{"name":"Bosnia and Herzegovina","link":"https:\/\/turfutils.github.io\/cache\/altscore_b\/2025-05\/2025-05_268.html"},{"name":"Barbados","link":"https:\/\/turfutils.github.io\/cache\/altscore_b\/2025-05\/2025-05_269.html"},{"name":"Greenland","link":"https:\/\/turfutils.github.io\/cache\/altscore_b\/2025-05\/2025-05_270.html"},{"name":"Chad","link":"https:\/\/turfutils.github.io\/cache\/altscore_b\/2025-05\/2025-05_271.html"},{"name":"Cambodia","link":"https:\/\/turfutils.github.io\/cache\/altscore_b\/2025-05\/2025-05_272.html"},{"name":"Russia","link":"https:\/\/turfutils.github.io\/cache\/altscore_b\/2025-05\/2025-05_273.html"},{"name":"Belarus","link":"https:\/\/turfutils.github.io\/cache\/altscore_b\/2025-05\/2025-05_274.html"},{"name":"Kenya","link":"https:\/\/turfutils.github.io\/cache\/altscore_b\/2025-05\/2025-05_275.html"},{"name":"Ethiopia","link":"https:\/\/turfutils.github.io\/cache\/altscore_b\/2025-05\/2025-05_276.html"},{"name":"Senegal","link":"https:\/\/turfutils.github.io\/cache\/altscore_b\/2025-05\/2025-05_277.html"},{"name":"Israel","link":"https:\/\/turfutils.github.io\/cache\/altscore_b\/2025-05\/2025-05_278.html"},{"name":"Gibraltar","link":"https:\/\/turfutils.github.io\/cache\/altscore_b\/2025-05\/2025-05_279.html"},{"name":"Romania","link":"https:\/\/turfutils.github.io\/cache\/altscore_b\/2025-05\/2025-05_280.html"},{"name":"Central African Republic","link":"https:\/\/turfutils.github.io\/cache\/altscore_b\/2025-05\/2025-05_281.html"},{"name":"Cameroon","link":"https:\/\/turfutils.github.io\/cache\/altscore_b\/2025-05\/2025-05_282.html"},{"name":"Burkina Faso","link":"https:\/\/turfutils.github.io\/cache\/altscore_b\/2025-05\/2025-05_283.html"},{"name":"Afghanistan","link":"https:\/\/turfutils.github.io\/cache\/altscore_b\/2025-05\/2025-05_284.html"},{"name":"Armenia","link":"https:\/\/turfutils.github.io\/cache\/altscore_b\/2025-05\/2025-05_285.html"},{"name":"Albania","link":"https:\/\/turfutils.github.io\/cache\/altscore_b\/2025-05\/2025-05_286.html"},{"name":"Andorra","link":"https:\/\/turfutils.github.io\/cache\/altscore_b\/2025-05\/2025-05_287.html"},{"name":"Azerbaijan","link":"https:\/\/turfutils.github.io\/cache\/altscore_b\/2025-05\/2025-05_288.html"},{"name":"Bahrain","link":"https:\/\/turfutils.github.io\/cache\/altscore_b\/2025-05\/2025-05_289.html"},{"name":"Botswana","link":"https:\/\/turfutils.github.io\/cache\/altscore_b\/2025-05\/2025-05_290.html"},{"name":"Zimbabwe","link":"https:\/\/turfutils.github.io\/cache\/altscore_b\/2025-05\/2025-05_291.html"},{"name":"Viet Nam","link":"https:\/\/turfutils.github.io\/cache\/altscore_b\/2025-05\/2025-05_292.html"},{"name":"Benin","link":"https:\/\/turfutils.github.io\/cache\/altscore_b\/2025-05\/2025-05_293.html"},{"name":"C\u00f4te dIvoire","link":"https:\/\/turfutils.github.io\/cache\/altscore_b\/2025-05\/2025-05_294.html"},{"name":"Gambia","link":"https:\/\/turfutils.github.io\/cache\/altscore_b\/2025-05\/2025-05_295.html"},{"name":"Pitcairn Islands","link":"https:\/\/turfutils.github.io\/cache\/altscore_b\/2025-05\/2025-05_306.html"},{"name":"Fiji","link":"https:\/\/turfutils.github.io\/cache\/altscore_b\/2025-05\/2025-05_307.html"},{"name":"Dominica","link":"https:\/\/turfutils.github.io\/cache\/altscore_b\/2025-05\/2025-05_308.html"},{"name":"Bermuda","link":"https:\/\/turfutils.github.io\/cache\/altscore_b\/2025-05\/2025-05_309.html"},{"name":"Saint Helena","link":"https:\/\/turfutils.github.io\/cache\/altscore_b\/2025-05\/2025-05_310.html"},{"name":"Saint Kitts and Nevis","link":"https:\/\/turfutils.github.io\/cache\/altscore_b\/2025-05\/2025-05_311.html"},{"name":"Saint Lucia","link":"https:\/\/turfutils.github.io\/cache\/altscore_b\/2025-05\/2025-05_312.html"},{"name":"Ukraine","link":"https:\/\/turfutils.github.io\/cache\/altscore_b\/2025-05\/2025-05_313.html"},{"name":"Syria","link":"https:\/\/turfutils.github.io\/cache\/altscore_b\/2025-05\/2025-05_314.html"},{"name":"Iran","link":"https:\/\/turfutils.github.io\/cache\/altscore_b\/2025-05\/2025-05_315.html"},{"name":"Iraq","link":"https:\/\/turfutils.github.io\/cache\/altscore_b\/2025-05\/2025-05_316.html"},{"name":"Morocco","link":"https:\/\/turfutils.github.io\/cache\/altscore_b\/2025-05\/2025-05_317.html"},{"name":"Pakistan","link":"https:\/\/turfutils.github.io\/cache\/altscore_b\/2025-05\/2025-05_318.html"},{"name":"Palestine","link":"https:\/\/turfutils.github.io\/cache\/altscore_b\/2025-05\/2025-05_319.html"},{"name":"Algeria","link":"https:\/\/turfutils.github.io\/cache\/altscore_b\/2025-05\/2025-05_320.html"},{"name":"Bangladesh","link":"https:\/\/turfutils.github.io\/cache\/altscore_b\/2025-05\/2025-05_321.html"},{"name":"Congo-Kinshasa","link":"https:\/\/turfutils.github.io\/cache\/altscore_b\/2025-05\/2025-05_322.html"},{"name":"Georgia","link":"https:\/\/turfutils.github.io\/cache\/altscore_b\/2025-05\/2025-05_323.html"},{"name":"Indonesia","link":"https:\/\/turfutils.github.io\/cache\/altscore_b\/2025-05\/2025-05_324.html"},{"name":"Jordan","link":"https:\/\/turfutils.github.io\/cache\/altscore_b\/2025-05\/2025-05_325.html"},{"name":"Kazakhstan","link":"https:\/\/turfutils.github.io\/cache\/altscore_b\/2025-05\/2025-05_326.html"},{"name":"Kenya","link":"https:\/\/turfutils.github.io\/cache\/altscore_b\/2025-05\/2025-05_327.html"},{"name":"Lebanon","link":"https:\/\/turfutils.github.io\/cache\/altscore_b\/2025-05\/2025-05_328.html"},{"name":"Libya","link":"https:\/\/turfutils.github.io\/cache\/altscore_b\/2025-05\/2025-05_329.html"},{"name":"Madagascar","link":"https:\/\/turfutils.github.io\/cache\/altscore_b\/2025-05\/2025-05_330.html"},{"name":"Malaysia","link":"https:\/\/turfutils.github.io\/cache\/altscore_b\/2025-05\/2025-05_331.html"},{"name":"Mali","link":"https:\/\/turfutils.github.io\/cache\/altscore_b\/2025-05\/2025-05_332.html"},{"name":"Mongolia","link":"https:\/\/turfutils.github.io\/cache\/altscore_b\/2025-05\/2025-05_333.html"},{"name":"Nepal","link":"https:\/\/turfutils.github.io\/cache\/altscore_b\/2025-05\/2025-05_334.html"},{"name":"Oman","link":"https:\/\/turfutils.github.io\/cache\/altscore_b\/2025-05\/2025-05_335.html"},{"name":"Philippines","link":"https:\/\/turfutils.github.io\/cache\/altscore_b\/2025-05\/2025-05_336.html"},{"name":"Saudi Arabia","link":"https:\/\/turfutils.github.io\/cache\/altscore_b\/2025-05\/2025-05_337.html"},{"name":"Serbia","link":"https:\/\/turfutils.github.io\/cache\/altscore_b\/2025-05\/2025-05_338.html"},{"name":"South Africa","link":"https:\/\/turfutils.github.io\/cache\/altscore_b\/2025-05\/2025-05_339.html"},{"name":"Sri Lanka","link":"https:\/\/turfutils.github.io\/cache\/altscore_b\/2025-05\/2025-05_340.html"},{"name":"Tanzania","link":"https:\/\/turfutils.github.io\/cache\/altscore_b\/2025-05\/2025-05_342.html"},{"name":"North Macedonia","link":"https:\/\/turfutils.github.io\/cache\/altscore_b\/2025-05\/2025-05_343.html"},{"name":"Tunisia","link":"https:\/\/turfutils.github.io\/cache\/altscore_b\/2025-05\/2025-05_344.html"},{"name":"Turkmenistan","link":"https:\/\/turfutils.github.io\/cache\/altscore_b\/2025-05\/2025-05_345.html"},{"name":"Uganda","link":"https:\/\/turfutils.github.io\/cache\/altscore_b\/2025-05\/2025-05_346.html"},{"name":"Uzbekistan","link":"https:\/\/turfutils.github.io\/cache\/altscore_b\/2025-05\/2025-05_347.html"},{"name":"Yemen","link":"https:\/\/turfutils.github.io\/cache\/altscore_b\/2025-05\/2025-05_348.html"},{"name":"Liechtenstein","link":"https:\/\/turfutils.github.io\/cache\/altscore_b\/2025-05\/2025-05_351.html"},{"name":"India","link":"https:\/\/turfutils.github.io\/cache\/altscore_b\/2025-05\/2025-05_352.html"},{"name":"North Korea","link":"https:\/\/turfutils.github.io\/cache\/altscore_b\/2025-05\/2025-05_353.html"},{"name":"Gabon","link":"https:\/\/turfutils.github.io\/cache\/altscore_b\/2025-05\/2025-05_354.html"},{"name":"Ghana","link":"https:\/\/turfutils.github.io\/cache\/altscore_b\/2025-05\/2025-05_355.html"},{"name":"Haiti","link":"https:\/\/turfutils.github.io\/cache\/altscore_b\/2025-05\/2025-05_356.html"},{"name":"Kiribati","link":"https:\/\/turfutils.github.io\/cache\/altscore_b\/2025-05\/2025-05_357.html"},{"name":"Kyrgyzstan","link":"https:\/\/turfutils.github.io\/cache\/altscore_b\/2025-05\/2025-05_358.html"},{"name":"Laos","link":"https:\/\/turfutils.github.io\/cache\/altscore_b\/2025-05\/2025-05_359.html"},{"name":"Lesotho","link":"https:\/\/turfutils.github.io\/cache\/altscore_b\/2025-05\/2025-05_360.html"},{"name":"Malawi","link":"https:\/\/turfutils.github.io\/cache\/altscore_b\/2025-05\/2025-05_361.html"},{"name":"Mauritania","link":"https:\/\/turfutils.github.io\/cache\/altscore_b\/2025-05\/2025-05_362.html"},{"name":"Mauritius","link":"https:\/\/turfutils.github.io\/cache\/altscore_b\/2025-05\/2025-05_363.html"},{"name":"Montenegro","link":"https:\/\/turfutils.github.io\/cache\/altscore_b\/2025-05\/2025-05_364.html"},{"name":"Mozambique","link":"https:\/\/turfutils.github.io\/cache\/altscore_b\/2025-05\/2025-05_365.html"},{"name":"Myanmar","link":"https:\/\/turfutils.github.io\/cache\/altscore_b\/2025-05\/2025-05_366.html"},{"name":"Namibia","link":"https:\/\/turfutils.github.io\/cache\/altscore_b\/2025-05\/2025-05_367.html"},{"name":"Niger","link":"https:\/\/turfutils.github.io\/cache\/altscore_b\/2025-05\/2025-05_368.html"},{"name":"Nigeria","link":"https:\/\/turfutils.github.io\/cache\/altscore_b\/2025-05\/2025-05_369.html"},{"name":"Palau","link":"https:\/\/turfutils.github.io\/cache\/altscore_b\/2025-05\/2025-05_370.html"},{"name":"Papua New Guinea","link":"https:\/\/turfutils.github.io\/cache\/altscore_b\/2025-05\/2025-05_371.html"},{"name":"Qatar","link":"https:\/\/turfutils.github.io\/cache\/altscore_b\/2025-05\/2025-05_372.html"},{"name":"Seychelles","link":"https:\/\/turfutils.github.io\/cache\/altscore_b\/2025-05\/2025-05_373.html"},{"name":"Slovenia","link":"https:\/\/turfutils.github.io\/cache\/altscore_b\/2025-05\/2025-05_374.html"},{"name":"Solomon Islands","link":"https:\/\/turfutils.github.io\/cache\/altscore_b\/2025-05\/2025-05_375.html"},{"name":"Sudan","link":"https:\/\/turfutils.github.io\/cache\/altscore_b\/2025-05\/2025-05_376.html"},{"name":"Suriname","link":"https:\/\/turfutils.github.io\/cache\/altscore_b\/2025-05\/2025-05_377.html"},{"name":"Tajikistan","link":"https:\/\/turfutils.github.io\/cache\/altscore_b\/2025-05\/2025-05_378.html"},{"name":"Togo","link":"https:\/\/turfutils.github.io\/cache\/altscore_b\/2025-05\/2025-05_379.html"},{"name":"United Arab Emirates","link":"https:\/\/turfutils.github.io\/cache\/altscore_b\/2025-05\/2025-05_380.html"},{"name":"Vanuatu","link":"https:\/\/turfutils.github.io\/cache\/altscore_b\/2025-05\/2025-05_381.html"},{"name":"Marshall Islands","link":"https:\/\/turfutils.github.io\/cache\/altscore_b\/2025-05\/2025-05_382.html"},{"name":"Vatican City","link":"https:\/\/turfutils.github.io\/cache\/altscore_b\/2025-05\/2025-05_384.html"},{"name":"Faroe Islands","link":"https:\/\/turfutils.github.io\/cache\/altscore_b\/2025-05\/2025-05_385.html"},{"name":"Cura\u00e7ao","link":"https:\/\/turfutils.github.io\/cache\/altscore_b\/2025-05\/2025-05_387.html"},{"name":"Swaziland","link":"https:\/\/turfutils.github.io\/cache\/altscore_b\/2025-05\/2025-05_389.html"},{"name":"Moldova","link":"https:\/\/turfutils.github.io\/cache\/altscore_b\/2025-05\/2025-05_398.html"},{"name":"San Marino","link":"https:\/\/turfutils.github.io\/cache\/altscore_b\/2025-05\/2025-05_399.html"},{"name":"Antigua and Barbuda","link":"https:\/\/turfutils.github.io\/cache\/altscore_b\/2025-05\/2025-05_400.html"},{"name":"Micronesia","link":"https:\/\/turfutils.github.io\/cache\/altscore_b\/2025-05\/2025-05_401.html"},{"name":"Angola","link":"https:\/\/turfutils.github.io\/cache\/altscore_b\/2025-05\/2025-05_402.html"},{"name":"Eritrea","link":"https:\/\/turfutils.github.io\/cache\/altscore_b\/2025-05\/2025-05_403.html"},{"name":"Maldives","link":"https:\/\/turfutils.github.io\/cache\/altscore_b\/2025-05\/2025-05_416.html"},{"name":"Monaco","link":"https:\/\/turfutils.github.io\/cache\/altscore_b\/2025-05\/2025-05_427.html"},{"name":"Jersey","link":"https:\/\/turfutils.github.io\/cache\/altscore_b\/2025-05\/2025-05_428.html"},{"name":"Guernsey","link":"https:\/\/turfutils.github.io\/cache\/altscore_b\/2025-05\/2025-05_429.html"},{"name":"Isle of Man","link":"https:\/\/turfutils.github.io\/cache\/altscore_b\/2025-05\/2025-05_456.html"},{"name":"Guinea-Bissau","link":"https:\/\/turfutils.github.io\/cache\/altscore_b\/2025-05\/2025-05_457.html"},{"name":"Liberia","link":"https:\/\/turfutils.github.io\/cache\/altscore_b\/2025-05\/2025-05_458.html"},{"name":"South Sudan","link":"https:\/\/turfutils.github.io\/cache\/altscore_b\/2025-05\/2025-05_459.html"},{"name":"Equatorial Guinea","link":"https:\/\/turfutils.github.io\/cache\/altscore_b\/2025-05\/2025-05_460.html"},{"name":"Djibouti","link":"https:\/\/turfutils.github.io\/cache\/altscore_b\/2025-05\/2025-05_461.html"},{"name":"Somalia","link":"https:\/\/turfutils.github.io\/cache\/altscore_b\/2025-05\/2025-05_462.html"},{"name":"Congo-Brazzaville","link":"https:\/\/turfutils.github.io\/cache\/altscore_b\/2025-05\/2025-05_463.html"},{"name":"Kosovo and Metohija","link":"https:\/\/turfutils.github.io\/cache\/altscore_b\/2025-05\/2025-05_464.html"},{"name":"French Polynesia","link":"https:\/\/turfutils.github.io\/cache\/altscore_b\/2025-05\/2025-05_465.html"},{"name":"Sierra Leone","link":"https:\/\/turfutils.github.io\/cache\/altscore_b\/2025-05\/2025-05_466.html"},{"name":"Guinea","link":"https:\/\/turfutils.github.io\/cache\/altscore_b\/2025-05\/2025-05_467.html"},{"name":"Trinidad and Tobago","link":"https:\/\/turfutils.github.io\/cache\/altscore_b\/2025-05\/2025-05_468.html"},{"name":"Bhutan","link":"https:\/\/turfutils.github.io\/cache\/altscore_b\/2025-05\/2025-05_469.html"}]},{"name":"kr","subcategories":[{"name":"ALL","link":"https:\/\/turfutils.github.io\/cache\/altscore_b\/2025-05\/2025-05_kr.html"},{"name":"Seoul","link":"https:\/\/turfutils.github.io\/cache\/altscore_b\/2025-05\/2025-05_157.html"},{"name":"Busan","link":"https:\/\/turfutils.github.io\/cache\/altscore_b\/2025-05\/2025-05_158.html"},{"name":"Daegu","link":"https:\/\/turfutils.github.io\/cache\/altscore_b\/2025-05\/2025-05_159.html"},{"name":"Gwangju","link":"https:\/\/turfutils.github.io\/cache\/altscore_b\/2025-05\/2025-05_160.html"},{"name":"Daejeon","link":"https:\/\/turfutils.github.io\/cache\/altscore_b\/2025-05\/2025-05_161.html"},{"name":"Incheon","link":"https:\/\/turfutils.github.io\/cache\/altscore_b\/2025-05\/2025-05_162.html"},{"name":"Ulsan","link":"https:\/\/turfutils.github.io\/cache\/altscore_b\/2025-05\/2025-05_163.html"},{"name":"Gyeonggi","link":"https:\/\/turfutils.github.io\/cache\/altscore_b\/2025-05\/2025-05_164.html"},{"name":"Gangwon","link":"https:\/\/turfutils.github.io\/cache\/altscore_b\/2025-05\/2025-05_165.html"},{"name":"Chungcheongbuk","link":"https:\/\/turfutils.github.io\/cache\/altscore_b\/2025-05\/2025-05_166.html"},{"name":"Chungcheongnam","link":"https:\/\/turfutils.github.io\/cache\/altscore_b\/2025-05\/2025-05_167.html"},{"name":"Jeollabuk","link":"https:\/\/turfutils.github.io\/cache\/altscore_b\/2025-05\/2025-05_168.html"},{"name":"Jeollanam","link":"https:\/\/turfutils.github.io\/cache\/altscore_b\/2025-05\/2025-05_169.html"},{"name":"Gyeongsangbuk","link":"https:\/\/turfutils.github.io\/cache\/altscore_b\/2025-05\/2025-05_170.html"},{"name":"Gyeongsangnam","link":"https:\/\/turfutils.github.io\/cache\/altscore_b\/2025-05\/2025-05_171.html"}]},{"name":"dk","subcategories":[{"name":"ALL","link":"https:\/\/turfutils.github.io\/cache\/altscore_b\/2025-05\/2025-05_dk.html"},{"name":"Hovedstaden","link":"https:\/\/turfutils.github.io\/cache\/altscore_b\/2025-05\/2025-05_172.html"},{"name":"Sj\u00e6lland","link":"https:\/\/turfutils.github.io\/cache\/altscore_b\/2025-05\/2025-05_173.html"},{"name":"Syddanmark","link":"https:\/\/turfutils.github.io\/cache\/altscore_b\/2025-05\/2025-05_174.html"},{"name":"Midtjylland","link":"https:\/\/turfutils.github.io\/cache\/altscore_b\/2025-05\/2025-05_175.html"},{"name":"Nordjylland","link":"https:\/\/turfutils.github.io\/cache\/altscore_b\/2025-05\/2025-05_176.html"}]},{"name":"fi","subcategories":[{"name":"ALL","link":"https:\/\/turfutils.github.io\/cache\/altscore_b\/2025-05\/2025-05_fi.html"},{"name":"\u00c5land","link":"https:\/\/turfutils.github.io\/cache\/altscore_b\/2025-05\/2025-05_177.html"},{"name":"Lounais-Suomi","link":"https:\/\/turfutils.github.io\/cache\/altscore_b\/2025-05\/2025-05_184.html"},{"name":"Etel\u00e4-Suomi","link":"https:\/\/turfutils.github.io\/cache\/altscore_b\/2025-05\/2025-05_185.html"},{"name":"L\u00e4nsi- ja Sis\u00e4-Suomi","link":"https:\/\/turfutils.github.io\/cache\/altscore_b\/2025-05\/2025-05_186.html"},{"name":"It\u00e4-Suomi","link":"https:\/\/turfutils.github.io\/cache\/altscore_b\/2025-05\/2025-05_187.html"},{"name":"Pohjois-Suomi","link":"https:\/\/turfutils.github.io\/cache\/altscore_b\/2025-05\/2025-05_188.html"},{"name":"Lappi","link":"https:\/\/turfutils.github.io\/cache\/altscore_b\/2025-05\/2025-05_189.html"}]},{"name":"no","subcategories":[{"name":"ALL","link":"https:\/\/turfutils.github.io\/cache\/altscore_b\/2025-05\/2025-05_no.html"},{"name":"\u00d8stlandet","link":"https:\/\/turfutils.github.io\/cache\/altscore_b\/2025-05\/2025-05_179.html"},{"name":"S\u00f8rlandet","link":"https:\/\/turfutils.github.io\/cache\/altscore_b\/2025-05\/2025-05_180.html"},{"name":"Vestlandet","link":"https:\/\/turfutils.github.io\/cache\/altscore_b\/2025-05\/2025-05_181.html"},{"name":"Tr\u00f8ndelag","link":"https:\/\/turfutils.github.io\/cache\/altscore_b\/2025-05\/2025-05_182.html"},{"name":"Nordnorge","link":"https:\/\/turfutils.github.io\/cache\/altscore_b\/2025-05\/2025-05_183.html"}]},{"name":"us","subcategories":[{"name":"ALL","link":"https:\/\/turfutils.github.io\/cache\/altscore_b\/2025-05\/2025-05_us.html"},{"name":"California","link":"https:\/\/turfutils.github.io\/cache\/altscore_b\/2025-05\/2025-05_190.html"},{"name":"Virginia","link":"https:\/\/turfutils.github.io\/cache\/altscore_b\/2025-05\/2025-05_191.html"},{"name":"New York","link":"https:\/\/turfutils.github.io\/cache\/altscore_b\/2025-05\/2025-05_210.html"},{"name":"Florida","link":"https:\/\/turfutils.github.io\/cache\/altscore_b\/2025-05\/2025-05_226.html"},{"name":"Arizona","link":"https:\/\/turfutils.github.io\/cache\/altscore_b\/2025-05\/2025-05_227.html"},{"name":"Nevada","link":"https:\/\/turfutils.github.io\/cache\/altscore_b\/2025-05\/2025-05_240.html"},{"name":"Massachusetts","link":"https:\/\/turfutils.github.io\/cache\/altscore_b\/2025-05\/2025-05_241.html"},{"name":"Hawaii","link":"https:\/\/turfutils.github.io\/cache\/altscore_b\/2025-05\/2025-05_296.html"},{"name":"Pennsylvania","link":"https:\/\/turfutils.github.io\/cache\/altscore_b\/2025-05\/2025-05_297.html"},{"name":"Tennessee","link":"https:\/\/turfutils.github.io\/cache\/altscore_b\/2025-05\/2025-05_298.html"},{"name":"Kentucky","link":"https:\/\/turfutils.github.io\/cache\/altscore_b\/2025-05\/2025-05_299.html"},{"name":"Illinois","link":"https:\/\/turfutils.github.io\/cache\/altscore_b\/2025-05\/2025-05_300.html"},{"name":"Louisiana","link":"https:\/\/turfutils.github.io\/cache\/altscore_b\/2025-05\/2025-05_301.html"},{"name":"Alaska","link":"https:\/\/turfutils.github.io\/cache\/altscore_b\/2025-05\/2025-05_302.html"},{"name":"Wyoming","link":"https:\/\/turfutils.github.io\/cache\/altscore_b\/2025-05\/2025-05_303.html"},{"name":"Colorado","link":"https:\/\/turfutils.github.io\/cache\/altscore_b\/2025-05\/2025-05_304.html"},{"name":"New Mexico","link":"https:\/\/turfutils.github.io\/cache\/altscore_b\/2025-05\/2025-05_305.html"},{"name":"Washington","link":"https:\/\/turfutils.github.io\/cache\/altscore_b\/2025-05\/2025-05_349.html"},{"name":"District of Columbia","link":"https:\/\/turfutils.github.io\/cache\/altscore_b\/2025-05\/2025-05_350.html"},{"name":"Texas","link":"https:\/\/turfutils.github.io\/cache\/altscore_b\/2025-05\/2025-05_386.html"},{"name":"Maryland","link":"https:\/\/turfutils.github.io\/cache\/altscore_b\/2025-05\/2025-05_388.html"},{"name":"Minnesota","link":"https:\/\/turfutils.github.io\/cache\/altscore_b\/2025-05\/2025-05_405.html"},{"name":"New Jersey","link":"https:\/\/turfutils.github.io\/cache\/altscore_b\/2025-05\/2025-05_406.html"},{"name":"Maine","link":"https:\/\/turfutils.github.io\/cache\/altscore_b\/2025-05\/2025-05_407.html"},{"name":"Oregon","link":"https:\/\/turfutils.github.io\/cache\/altscore_b\/2025-05\/2025-05_408.html"},{"name":"Connecticut","link":"https:\/\/turfutils.github.io\/cache\/altscore_b\/2025-05\/2025-05_409.html"},{"name":"Utah","link":"https:\/\/turfutils.github.io\/cache\/altscore_b\/2025-05\/2025-05_410.html"},{"name":"South Dakota","link":"https:\/\/turfutils.github.io\/cache\/altscore_b\/2025-05\/2025-05_411.html"},{"name":"Wisconsin","link":"https:\/\/turfutils.github.io\/cache\/altscore_b\/2025-05\/2025-05_412.html"},{"name":"Michigan","link":"https:\/\/turfutils.github.io\/cache\/altscore_b\/2025-05\/2025-05_413.html"},{"name":"Vermont","link":"https:\/\/turfutils.github.io\/cache\/altscore_b\/2025-05\/2025-05_414.html"},{"name":"Minor Outlying Islands","link":"https:\/\/turfutils.github.io\/cache\/altscore_b\/2025-05\/2025-05_415.html"},{"name":"Montana","link":"https:\/\/turfutils.github.io\/cache\/altscore_b\/2025-05\/2025-05_417.html"},{"name":"Idaho","link":"https:\/\/turfutils.github.io\/cache\/altscore_b\/2025-05\/2025-05_418.html"},{"name":"North Dakota","link":"https:\/\/turfutils.github.io\/cache\/altscore_b\/2025-05\/2025-05_419.html"},{"name":"Nebraska","link":"https:\/\/turfutils.github.io\/cache\/altscore_b\/2025-05\/2025-05_420.html"},{"name":"Iowa","link":"https:\/\/turfutils.github.io\/cache\/altscore_b\/2025-05\/2025-05_421.html"},{"name":"Kansas","link":"https:\/\/turfutils.github.io\/cache\/altscore_b\/2025-05\/2025-05_422.html"},{"name":"Indiana","link":"https:\/\/turfutils.github.io\/cache\/altscore_b\/2025-05\/2025-05_423.html"},{"name":"Ohio","link":"https:\/\/turfutils.github.io\/cache\/altscore_b\/2025-05\/2025-05_424.html"},{"name":"New Hampshire","link":"https:\/\/turfutils.github.io\/cache\/altscore_b\/2025-05\/2025-05_425.html"},{"name":"Delaware","link":"https:\/\/turfutils.github.io\/cache\/altscore_b\/2025-05\/2025-05_426.html"},{"name":"North Carolina","link":"https:\/\/turfutils.github.io\/cache\/altscore_b\/2025-05\/2025-05_430.html"},{"name":"South Carolina","link":"https:\/\/turfutils.github.io\/cache\/altscore_b\/2025-05\/2025-05_431.html"},{"name":"Georgia","link":"https:\/\/turfutils.github.io\/cache\/altscore_b\/2025-05\/2025-05_432.html"},{"name":"West Virginia","link":"https:\/\/turfutils.github.io\/cache\/altscore_b\/2025-05\/2025-05_433.html"},{"name":"Alabama","link":"https:\/\/turfutils.github.io\/cache\/altscore_b\/2025-05\/2025-05_434.html"},{"name":"Arkansas","link":"https:\/\/turfutils.github.io\/cache\/altscore_b\/2025-05\/2025-05_435.html"},{"name":"Missouri","link":"https:\/\/turfutils.github.io\/cache\/altscore_b\/2025-05\/2025-05_436.html"},{"name":"Oklahoma","link":"https:\/\/turfutils.github.io\/cache\/altscore_b\/2025-05\/2025-05_437.html"},{"name":"Mississippi","link":"https:\/\/turfutils.github.io\/cache\/altscore_b\/2025-05\/2025-05_454.html"},{"name":"Rhode Island","link":"https:\/\/turfutils.github.io\/cache\/altscore_b\/2025-05\/2025-05_455.html"}]},{"name":"is","subcategories":[{"name":"ALL","link":"https:\/\/turfutils.github.io\/cache\/altscore_b\/2025-05\/2025-05_is.html"},{"name":"Reykjav\u00edk","link":"https:\/\/turfutils.github.io\/cache\/altscore_b\/2025-05\/2025-05_192.html"},{"name":"Dreifb\u00fdli","link":"https:\/\/turfutils.github.io\/cache\/altscore_b\/2025-05\/2025-05_209.html"}]},{"name":"gb","subcategories":[{"name":"ALL","link":"https:\/\/turfutils.github.io\/cache\/altscore_b\/2025-05\/2025-05_gb.html"},{"name":"South West England","link":"https:\/\/turfutils.github.io\/cache\/altscore_b\/2025-05\/2025-05_197.html"},{"name":"Wales","link":"https:\/\/turfutils.github.io\/cache\/altscore_b\/2025-05\/2025-05_198.html"},{"name":"North East England","link":"https:\/\/turfutils.github.io\/cache\/altscore_b\/2025-05\/2025-05_199.html"},{"name":"Scotland","link":"https:\/\/turfutils.github.io\/cache\/altscore_b\/2025-05\/2025-05_200.html"},{"name":"North West England","link":"https:\/\/turfutils.github.io\/cache\/altscore_b\/2025-05\/2025-05_201.html"},{"name":"Yorkshire & The Humber","link":"https:\/\/turfutils.github.io\/cache\/altscore_b\/2025-05\/2025-05_202.html"},{"name":"East Midlands","link":"https:\/\/turfutils.github.io\/cache\/altscore_b\/2025-05\/2025-05_203.html"},{"name":"East of England","link":"https:\/\/turfutils.github.io\/cache\/altscore_b\/2025-05\/2025-05_204.html"},{"name":"South East England","link":"https:\/\/turfutils.github.io\/cache\/altscore_b\/2025-05\/2025-05_205.html"},{"name":"Northern Ireland","link":"https:\/\/turfutils.github.io\/cache\/altscore_b\/2025-05\/2025-05_206.html"},{"name":"Greater London","link":"https:\/\/turfutils.github.io\/cache\/altscore_b\/2025-05\/2025-05_207.html"},{"name":"West Midlands","link":"https:\/\/turfutils.github.io\/cache\/altscore_b\/2025-05\/2025-05_208.html"},{"name":"-","link":"https:\/\/turfutils.github.io\/cache\/altscore_b\/2025-05\/2025-05_404.html"}]},{"name":"jp","subcategories":[{"name":"ALL","link":"https:\/\/turfutils.github.io\/cache\/altscore_b\/2025-05\/2025-05_jp.html"},{"name":"Kansai","link":"https:\/\/turfutils.github.io\/cache\/altscore_b\/2025-05\/2025-05_390.html"},{"name":"Hokkaido","link":"https:\/\/turfutils.github.io\/cache\/altscore_b\/2025-05\/2025-05_391.html"},{"name":"T\u014dhoku","link":"https:\/\/turfutils.github.io\/cache\/altscore_b\/2025-05\/2025-05_392.html"},{"name":"Ch\u016bgoku","link":"https:\/\/turfutils.github.io\/cache\/altscore_b\/2025-05\/2025-05_393.html"},{"name":"Ch\u016bbu","link":"https:\/\/turfutils.github.io\/cache\/altscore_b\/2025-05\/2025-05_394.html"},{"name":"Shikoku","link":"https:\/\/turfutils.github.io\/cache\/altscore_b\/2025-05\/2025-05_395.html"},{"name":"Kant\u014d","link":"https:\/\/turfutils.github.io\/cache\/altscore_b\/2025-05\/2025-05_396.html"},{"name":"Ky\u016bsh\u016b Okinawa","link":"https:\/\/turfutils.github.io\/cache\/altscore_b\/2025-05\/2025-05_397.html"}]},{"name":"de","subcategories":[{"name":"ALL","link":"https:\/\/turfutils.github.io\/cache\/altscore_b\/2025-05\/2025-05_de.html"},{"name":"Bremen","link":"https:\/\/turfutils.github.io\/cache\/altscore_b\/2025-05\/2025-05_438.html"},{"name":"Hamburg","link":"https:\/\/turfutils.github.io\/cache\/altscore_b\/2025-05\/2025-05_439.html"},{"name":"Berlin","link":"https:\/\/turfutils.github.io\/cache\/altscore_b\/2025-05\/2025-05_440.html"},{"name":"Brandenburg","link":"https:\/\/turfutils.github.io\/cache\/altscore_b\/2025-05\/2025-05_441.html"},{"name":"Mecklenburg-Vorpommern","link":"https:\/\/turfutils.github.io\/cache\/altscore_b\/2025-05\/2025-05_442.html"},{"name":"Schleswig-Holstein","link":"https:\/\/turfutils.github.io\/cache\/altscore_b\/2025-05\/2025-05_443.html"},{"name":"Niedersachsen","link":"https:\/\/turfutils.github.io\/cache\/altscore_b\/2025-05\/2025-05_444.html"},{"name":"Nordrhein-Westfalen","link":"https:\/\/turfutils.github.io\/cache\/altscore_b\/2025-05\/2025-05_445.html"},{"name":"Rheinland-Pfalz","link":"https:\/\/turfutils.github.io\/cache\/altscore_b\/2025-05\/2025-05_446.html"},{"name":"Saarland","link":"https:\/\/turfutils.github.io\/cache\/altscore_b\/2025-05\/2025-05_447.html"},{"name":"Baden-W\u00fcrttemberg","link":"https:\/\/turfutils.github.io\/cache\/altscore_b\/2025-05\/2025-05_448.html"},{"name":"Bayern","link":"https:\/\/turfutils.github.io\/cache\/altscore_b\/2025-05\/2025-05_449.html"},{"name":"Hessen","link":"https:\/\/turfutils.github.io\/cache\/altscore_b\/2025-05\/2025-05_450.html"},{"name":"Th\u00fcringen","link":"https:\/\/turfutils.github.io\/cache\/altscore_b\/2025-05\/2025-05_451.html"},{"name":"Sachsen","link":"https:\/\/turfutils.github.io\/cache\/altscore_b\/2025-05\/2025-05_452.html"},{"name":"Sachsen-Anhalt","link":"https:\/\/turfutils.github.io\/cache\/altscore_b\/2025-05\/2025-05_453.html"}]}]}