[{"CHANGE":"-","PLACE":1,"OLD":1,"NAME":"<a href=\"https:\/\/frut.zundin.se\/user_round.php?userid=morm&roundid=179\" target=\"_blank\" rel=\"noopener noreferrer\">morm<\/a>","ALTSCORE":"1208","DIFF":"30%","TOTAL_SCORE":"3995","COUNTRY":"<a href=\"https:\/\/turfmedals.com\/profile\/morm\" target=\"_blank\" rel=\"noopener noreferrer\"><img src=\"https:\/\/flagcdn.com\/h20\/.png\" height=\"20\" alt=\"\"><\/a>","REGION_NAME":"Austria","TOTAL_TAKES":"11","UNIQUE_ZONES":"11","DISTANCE":"  0","DURATION":"0.0"}]